rung2-quantizer/rtl/quantizer.sv
module quantizer #(
parameter int INPUT_WIDTH = 16,
parameter int OUTPUT_WIDTH = 8

)
(
    input logic clk,
    input logic rst_n,
    input logic valid_in,
    input logic signed [INPUT_WIDTH-1:0] data_in,
    input logic [7:0] scale,
    input logic round_mode,
    output logic signed [OUTPUT_WIDTH-1:0] data_out,
    output logic valid_out,
    output logic overflow

);

// internal signals
    logic signed [23:0] scaled;
    logic signed [23:0] rounded;
    logic signed [23:0] saturated;

    // stage 1 — scale
    assign scaled = data_in * $signed({1'b0, scale});

    //stage 2 - round
    always_comb begin
        if(round_mode == 1'b0)
            rounded = scaled;
        else 
            rounded = scaled + 24'sh1;
    end

    // stage 3 — saturate
    localparam signed [23:0] MAX_VAL = (2**(OUTPUT_WIDTH-1)) - 1;
    localparam signed [23:0] MIN_VAL = -(2**(OUTPUT_WIDTH-1));

    always_comb begin
        if (rounded > MAX_VAL) begin
            saturated = MAX_VAL;
            overflow  = 1'b1;
        end else if (rounded < MIN_VAL) begin
            saturated = MIN_VAL;
            overflow  = 1'b1;
        end else begin
            saturated = rounded;
            overflow  = 1'b0;
        end
    end

    // stage 4 — register output
    always_ff @(posedge clk or negedge rst_n) begin
        if (!rst_n) begin
            data_out  <= '0;
            valid_out <= 1'b0;
        end else if (valid_in) begin
            data_out  <= saturated[OUTPUT_WIDTH-1:0];
            valid_out <= 1'b1;
        end
    end

    endmodule

rung2-quantizer/tb/quantizer_tb.sv
`timescale 1ns/1ps

module quantizer_tb;
    logic clk;
    logic rst_n;
    logic valid_in;
    logic signed [15:0] data_in;
    logic [7:0] scale;
    logic round_mode;
    logic signed [7:0] data_out;
    logic valid_out;
    logic overflow;


quantizer #(.INPUT_WIDTH(16), .OUTPUT_WIDTH(8)) dut (.*);
always #5 clk = ~clk;

task automatic send(input signed [15:0] data_in_tb, input round_mode_tb, input [7:0] scale_tb);
    data_in= data_in_tb; round_mode = round_mode_tb; scale = scale_tb; valid_in = 1;
    @(posedge clk); #1;
    valid_in = 0;
endtask

task automatic check(input signed [7:0] expected, input expected_overflow, input string label);
    @(posedge clk); #1;
    if(data_out !== expected || overflow !== expected_overflow)
        $display("FAIL [%s]: got %0d expected %0d", label, data_out, expected);
    else
        $display("PASS [%s]: data_out = %0d", label, data_out);
endtask

initial begin
    $dumpfile("sim/waves.vcd");
    $dumpvars(0, quantizer_tb);

    clk = 0; rst_n = 0; valid_in = 0;
    data_in = 0; scale = 0; round_mode = 0;
    @(posedge clk); #1;
    rst_n = 1;

    // original 4 directed tests
    send(5, 0, 3);
    check(15, 0, "normal");

    send(32767, 0, 255);
    check(127, 1, "saturation");

    send(-30, 0, 3);
    check(-90, 0, "negative");

    send(10, 1, 3);
    check(31, 0, "rounding");

    // 1000 random vectors from golden.txt
    begin
        integer fd;
        integer status;
        logic signed [15:0] f_data_in;
        logic [7:0]         f_scale;
        logic               f_round_mode;
        logic signed [7:0]  f_expected;
        logic               f_overflow;
        integer             vec_num;
        integer             pass_count;
        integer             fail_count;

        fd = $fopen("tb/golden.txt", "r");
        if (fd == 0) begin
            $display("ERROR: could not open golden.txt");
            $finish;
        end

        vec_num    = 0;
        pass_count = 0;
        fail_count = 0;

        while (!$feof(fd)) begin
            status = $fscanf(fd, "%d %d %d %d %d\n",
                             f_data_in, f_scale, f_round_mode,
                             f_expected, f_overflow);
            if (status == 5) begin
                send(f_data_in, f_round_mode, f_scale);
                @(posedge clk); #1;
                if (data_out !== f_expected || overflow !== f_overflow) begin
                    $display("FAIL vec %0d: data_in=%0d scale=%0d mode=%0d got=%0d exp=%0d ovf=%0d exp_ovf=%0d",
                             vec_num, f_data_in, f_scale, f_round_mode,
                             data_out, f_expected, overflow, f_overflow);
                    fail_count = fail_count + 1;
                end else begin
                    pass_count = pass_count + 1;
                end
                vec_num = vec_num + 1;
            end
        end

        $fclose(fd);
        $display("\nRandom vectors: %0d passed, %0d failed", pass_count, fail_count);
    end

    $display("\nAll tests done.");
    $finish;
end

endmodule

rung2-quantizer/sim/waves.vcd
$date
	Wed May 27 15:06:55 2026
$end
$version
	Icarus Verilog
$end
$timescale
	1ps
$end
$scope module quantizer_tb $end
$var wire 1 ! valid_out $end
$var wire 1 " overflow $end
$var wire 8 # data_out [7:0] $end
$var reg 1 $ clk $end
$var reg 16 % data_in [15:0] $end
$var reg 1 & round_mode $end
$var reg 1 ' rst_n $end
$var reg 8 ( scale [7:0] $end
$var reg 1 ) valid_in $end
$scope module dut $end
$var wire 1 $ clk $end
$var wire 16 * data_in [15:0] $end
$var wire 1 & round_mode $end
$var wire 1 ' rst_n $end
$var wire 8 + scale [7:0] $end
$var wire 1 ) valid_in $end
$var wire 24 , scaled [23:0] $end
$var parameter 32 - INPUT_WIDTH $end
$var parameter 24 . MAX_VAL $end
$var parameter 24 / MIN_VAL $end
$var parameter 32 0 OUTPUT_WIDTH $end
$var reg 8 1 data_out [7:0] $end
$var reg 1 " overflow $end
$var reg 24 2 rounded [23:0] $end
$var reg 24 3 saturated [23:0] $end
$var reg 1 ! valid_out $end
$upscope $end
$scope begin $unm_blk_10 $end
$var reg 16 4 f_data_in [15:0] $end
$var reg 8 5 f_expected [7:0] $end
$var reg 1 6 f_overflow $end
$var reg 1 7 f_round_mode $end
$var reg 8 8 f_scale [7:0] $end
$var integer 32 9 fail_count [31:0] $end
$var integer 32 : fd [31:0] $end
$var integer 32 ; pass_count [31:0] $end
$var integer 32 < status [31:0] $end
$var integer 32 = vec_num [31:0] $end
$upscope $end
$scope task check $end
$upscope $end
$scope task send $end
$upscope $end
$upscope $end
$enddefinitions $end
$comment Show the parameter values. $end
$dumpall
b1000 0
b111111111111111110000000 /
b1111111 .
b10000 -
$end
#0
$dumpvars
bx =
bx <
bx ;
bx :
bx 9
bx 8
x7
x6
bx 5
bx 4
b0 3
b0 2
b0 1
b0 ,
b0 +
b0 *
0)
b0 (
0'
0&
b0 %
0$
b0 #
0"
0!
$end
#5000
1$
#6000
b1111 3
b1111 2
1)
b1111 ,
b11 (
b11 +
b101 %
b101 *
1'
#10000
0$
#15000
1!
b1111 #
b1111 1
1$
#16000
0)
#20000
0$
#25000
1$
#26000
1"
b1111111 3
b11111110111111100000001 2
1)
b11111111 (
b11111111 +
b11111110111111100000001 ,
b111111111111111 %
b111111111111111 *
#30000
0$
#35000
b1111111 #
b1111111 1
1$
#36000
0)
#40000
0$
#45000
1$
#46000
0"
b111111111111111110100110 3
b111111111111111110100110 2
1)
b11 (
b11 +
b111111111111111110100110 ,
b1111111111100010 %
b1111111111100010 *
#50000
0$
#55000
b10100110 #
b10100110 1
1$
#56000
0)
#60000
0$
#65000
1$
#66000
b11111 3
b11111 2
1)
1&
b11110 ,
b1010 %
b1010 *
#70000
0$
#75000
b11111 #
b11111 1
1$
#76000
0)
#80000
0$
#85000
1$
#86000
1"
b111111111111111110000000 3
b111000010011111001101000 2
1)
b1011000 (
b1011000 +
0&
b111000010011111001101000 ,
b1010011010000111 %
b1010011010000111 *
b101 <
16
b10000000 5
07
b1011000 8
b1010011010000111 4
b0 9
b0 ;
b0 =
b10000000000000000000000000000011 :
#90000
0$
#95000
b10000000 #
b10000000 1
1$
#96000
0)
#100000
0$
#105000
1$
#106000
b100110101111001110010001 2
1)
b11110110 (
b11110110 +
1&
b100110101111001110010000 ,
b1001011011011000 %
b1001011011011000 *
17
b11110110 8
b1001011011011000 4
b1 =
b1 ;
#110000
0$
#115000
1$
#116000
0)
#120000
0$
#125000
1$
#126000
b1111111 3
b1110111111011011010001 2
1)
b1111100 (
b1111100 +
b1110111111011011010000 ,
b111101111001100 %
b111101111001100 *
b1111111 5
b1111100 8
b111101111001100 4
b10 =
b10 ;
#130000
0$
#135000
b1111111 #
b1111111 1
1$
#136000
0)
#140000
0$
#145000
1$
#146000
b1001001111101011100000 2
1)
b10000111 (
b10000111 +
0&
b1001001111101011100000 ,
b100011000100000 %
b100011000100000 *
07
b10000111 8
b100011000100000 4
b11 =
b11 ;
#150000
0$
#155000
1$
#156000
0)
#160000
0$
#165000
1$
#166000
b101000111010111000001 2
1)
b101001 (
b101001 +
1&
b101000111010111000000 ,
b111111111000000 %
b111111111000000 *
17
b101001 8
b111111111000000 4
b100 =
b100 ;
#170000
0$
#175000
1$
#176000
0)
#180000
0$
#185000
1$
#186000
b10100101101010110001 2
1)
b1000011 (
b1000011 +
b10100101101010110000 ,
b10011110010000 %
b10011110010000 *
b1000011 8
b10011110010000 4
b101 =
b101 ;
#190000
0$
#195000
1$
#196000
0)
#200000
0$
#205000
1$
#206000
b111111111111111110000000 3
b111010110101100110100000 2
1)
b1111111 (
b1111111 +
0&
b111010110101100110100000 ,
b1101011001100000 %
b1101011001100000 *
b10000000 5
07
b1111111 8
b1101011001100000 4
b110 =
b110 ;
#210000
0$
#215000
b10000000 #
b10000000 1
1$
#216000
0)
#220000
0$
#225000
1$
#226000
b111111110101001111010100 2
1)
b1011 (
b1011 +
1&
b111111110101001111010011 ,
b1111000001011001 %
b1111000001011001 *
17
b1011 8
b1111000001011001 4
b111 =
b111 ;
#230000
0$
#235000
1$
#236000
0)
#240000
0$
#245000
1$
#246000
b101000000000111110111001 2
1)
b11101000 (
b11101000 +
b101000000000111110111000 ,
b1001011000100011 %
b1001011000100011 *
b11101000 8
b1001011000100011 4
b1000 =
b1000 ;
#250000
0$
#255000
1$
#256000
0)
#260000
0$
#265000
1$
#266000
b111111111010101000111110 2
1)
b101 (
b101 +
b111111111010101000111101 ,
b1110111011011001 %
b1110111011011001 *
b101 8
b1110111011011001 4
b1001 =
b1001 ;
#270000
0$
#275000
1$
#276000
0)
#280000
0$
#285000
1$
#286000
b110010100011101011111111 2
1)
b1111110 (
b1111110 +
b110010100011101011111110 ,
b1001001011000001 %
b1001001011000001 *
b1111110 8
b1001001011000001 4
b1010 =
b1010 ;
#290000
0$
#295000
1$
#296000
0)
#300000
0$
#305000
1$
#306000
b1111111 3
b110110100000010010001 2
1)
b1001100 (
b1001100 +
b110110100000010010000 ,
b101101111001100 %
b101101111001100 *
b1111111 5
b1001100 8
b101101111001100 4
b1011 =
b1011 ;
#310000
0$
#315000
b1111111 #
b1111111 1
1$
#316000
0)
#320000
0$
#325000
1$
#326000
b110000100111000100 2
1)
b1011011 (
b1011011 +
0&
b110000100111000100 ,
b100010001100 %
b100010001100 *
07
b1011011 8
b100010001100 4
b1100 =
b1100 ;
#330000
0$
#335000
1$
#336000
0)
#340000
0$
#345000
1$
#346000
b111111111111111110000000 3
b110010010101011101111100 2
1)
b10000100 (
b10000100 +
b110010010101011101111100 ,
b1001010111111111 %
b1001010111111111 *
b10000000 5
b10000100 8
b1001010111111111 4
b1101 =
b1101 ;
#350000
0$
#355000
b10000000 #
b10000000 1
1$
#356000
0)
#360000
0$
#365000
1$
#366000
b1111111 3
b101001011000011111010 2
1)
b1100010 (
b1100010 +
b101001011000011111010 ,
b11011000001101 %
b11011000001101 *
b1111111 5
b1100010 8
b11011000001101 4
b1110 =
b1110 ;
#370000
0$
#375000
b1111111 #
b1111111 1
1$
#376000
0)
#380000
0$
#385000
1$
#386000
b101011110011110101100 2
1)
b1101111 (
b1101111 +
1&
b101011110011110101011 ,
b11001010000101 %
b11001010000101 *
17
b1101111 8
b11001010000101 4
b1111 =
b1111 ;
#390000
0$
#395000
1$
#396000
0)
#400000
0$
#405000
1$
#406000
b1100001100111100 2
1)
b1100110 (
b1100110 +
0&
b1100001100111100 ,
b111101010 %
b111101010 *
07
b1100110 8
b111101010 4
b10000 =
b10000 ;
#410000
0$
#415000
1$
#416000
0)
#420000
0$
#425000
1$
#426000
b111111111111111110000000 3
b101111111000001100110000 2
1)
b11011000 (
b11011000 +
b101111111000001100110000 ,
b1011001110010010 %
b1011001110010010 *
b10000000 5
b11011000 8
b1011001110010010 4
b10001 =
b10001 ;
#430000
0$
#435000
b10000000 #
b10000000 1
1$
#436000
0)
#440000
0$
#445000
1$
#446000
b111011000100010000100000 2
1)
b101000 (
b101000 +
b111011000100010000100000 ,
b1000000110110100 %
b1000000110110100 *
b101000 8
b1000000110110100 4
b10010 =
b10010 ;
#450000
0$
#455000
1$
#456000
0)
#460000
0$
#465000
1$
#466000
b100110111100001000001101 2
1)
b11110111 (
b11110111 +
b100110111100001000001101 ,
b1001100000011011 %
b1001100000011011 *
b11110111 8
b1001100000011011 4
b10011 =
b10011 ;
#470000
0$
#475000
1$
#476000
0)
#480000
0$
#485000
1$
#486000
b111101111010101000010000 2
1)
b110000 (
b110000 +
b111101111010101000010000 ,
b1101001110001011 %
b1101001110001011 *
b110000 8
b1101001110001011 4
b10100 =
b10100 ;
#490000
0$
#495000
1$
#496000
0)
#500000
0$
#505000
1$
#506000
b1111111 3
b100011001000110010 2
1)
b1010011 (
b1010011 +
b100011001000110010 ,
b11011000110 %
b11011000110 *
b1111111 5
b1010011 8
b11011000110 4
b10101 =
b10101 ;
#510000
0$
#515000
b1111111 #
b1111111 1
1$
#516000
0)
#520000
0$
#525000
1$
#526000
b111111111111111110000000 3
b111111101010001100010001 2
1)
b1100 (
b1100 +
1&
b111111101010001100010000 ,
b1110001011101100 %
b1110001011101100 *
b10000000 5
17
b1100 8
b1110001011101100 4
b10110 =
b10110 ;
#530000
0$
#535000
b10000000 #
b10000000 1
1$
#536000
0)
#540000
0$
#545000
1$
#546000
b1111111 3
b11110000101001110111101 2
1)
b11111101 (
b11111101 +
0&
b11110000101001110111101 ,
b111100111000001 %
b111100111000001 *
b1111111 5
07
b11111101 8
b111100111000001 4
b10111 =
b10111 ;
#550000
0$
#555000
b1111111 #
b1111111 1
1$
#556000
0)
#560000
0$
#565000
1$
#566000
b111111111111111110000000 3
b111010101001100001000000 2
1)
b1011100 (
b1011100 +
b111010101001100001000000 ,
b1100010001110000 %
b1100010001110000 *
b10000000 5
b1011100 8
b1100010001110000 4
b11000 =
b11000 ;
#570000
0$
#575000
b10000000 #
b10000000 1
1$
#576000
0)
#580000
0$
#585000
1$
#586000
b1111111 3
b100110101010010000010 2
1)
b1010010 (
b1010010 +
b100110101010010000010 ,
b11110001011001 %
b11110001011001 *
b1111111 5
b1010010 8
b11110001011001 4
b11001 =
b11001 ;
#590000
0$
#595000
b1111111 #
b1111111 1
1$
#596000
0)
#600000
0$
#605000
1$
#606000
b111111111111111110000000 3
b101001010110011001001101 2
1)
b11001010 (
b11001010 +
1&
b101001010110011001001100 ,
b1000110100101110 %
b1000110100101110 *
b10000000 5
17
b11001010 8
b1000110100101110 4
b11010 =
b11010 ;
#610000
0$
#615000
b10000000 #
b10000000 1
1$
#616000
0)
#620000
0$
#625000
1$
#626000
b1111111 3
b10011110110000110110 2
1)
b100110 (
b100110 +
0&
b10011110110000110110 ,
b100001011011001 %
b100001011011001 *
b1111111 5
07
b100110 8
b100001011011001 4
b11011 =
b11011 ;
#630000
0$
#635000
b1111111 #
b1111111 1
1$
#636000
0)
#640000
0$
#645000
1$
#646000
b100100010100100111 2
1)
b11001 (
b11001 +
b100100010100100111 ,
b1011100111111 %
b1011100111111 *
b11001 8
b1011100111111 4
b11100 =
b11100 ;
#650000
0$
#655000
1$
#656000
0)
#660000
0$
#665000
1$
#666000
b1101010100011010101000 2
1)
b11110101 (
b11110101 +
1&
b1101010100011010100111 ,
b11011110101011 %
b11011110101011 *
17
b11110101 8
b11011110101011 4
b11101 =
b11101 ;
#670000
0$
#675000
1$
#676000
0)
#680000
0$
#685000
1$
#686000
b1011001100001001 2
1)
b1000100 (
b1000100 +
b1011001100001000 ,
b1010100010 %
b1010100010 *
b1000100 8
b1010100010 4
b11110 =
b11110 ;
#690000
0$
#695000
1$
#696000
0)
#700000
0$
#705000
1$
#706000
b10000001110111001101111 2
1)
b11100011 (
b11100011 +
b10000001110111001101110 ,
b100100100111010 %
b100100100111010 *
b11100011 8
b100100100111010 4
b11111 =
b11111 ;
#710000
0$
#715000
1$
#716000
0)
#720000
0$
#725000
1$
#726000
b1010110001000110010000 2
1)
b10001000 (
b10001000 +
0&
b1010110001000110010000 ,
b101000100010010 %
b101000100010010 *
07
b10001000 8
b101000100010010 4
b100000 =
b100000 ;
#730000
0$
#735000
1$
#736000
0)
#740000
0$
#745000
1$
#746000
b101111010011100 2
1)
b11100 (
b11100 +
b101111010011100 ,
b1101100001 %
b1101100001 *
b11100 8
b1101100001 4
b100001 =
b100001 ;
#750000
0$
#755000
1$
#756000
0)
#760000
0$
#765000
1$
#766000
b111111111111111110000000 3
b111000000110011111010011 2
1)
b1000111 (
b1000111 +
b111000000110011111010011 ,
b1000111000010101 %
b1000111000010101 *
b10000000 5
b1000111 8
b1000111000010101 4
b100010 =
b100010 ;
#770000
0$
#775000
b10000000 #
b10000000 1
1$
#776000
0)
#780000
0$
#785000
1$
#786000
b111101110111001000111101 2
1)
b10111 (
b10111 +
b111101110111001000111101 ,
b1010000011001011 %
b1010000011001011 *
b10111 8
b1010000011001011 4
b100011 =
b100011 ;
#790000
0$
#795000
1$
#796000
0)
#800000
0$
#805000
1$
#806000
b1111111 3
b110110001110100011101 2
1)
b1110001 (
b1110001 +
b110110001110100011101 ,
b11110101101101 %
b11110101101101 *
b1111111 5
b1110001 8
b11110101101101 4
b100100 =
b100100 ;
#810000
0$
#815000
b1111111 #
b1111111 1
1$
#816000
0)
#820000
0$
#825000
1$
#826000
b10000101110110011011001 2
1)
b11000101 (
b11000101 +
1&
b10000101110110011011000 ,
b101011011111000 %
b101011011111000 *
17
b11000101 8
b101011011111000 4
b100101 =
b100101 ;
#830000
0$
#835000
1$
#836000
0)
#840000
0$
#845000
1$
#846000
b111111111111111110000000 3
b111111101101001101111001 2
1)
b10100011 (
b10100011 +
b111111101101001101111000 ,
b1111111000101000 %
b1111111000101000 *
b10000000 5
b10100011 8
b1111111000101000 4
b100110 =
b100110 ;
#850000
0$
#855000
b10000000 #
b10000000 1
1$
#856000
0)
#860000
0$
#865000
1$
#866000
b111101101001000110101010 2
1)
b10111110 (
b10111110 +
0&
b111101101001000110101010 ,
b1111001101001011 %
b1111001101001011 *
07
b10111110 8
b1111001101001011 4
b100111 =
b100111 ;
#870000
0$
#875000
1$
#876000
0)
#880000
0$
#885000
1$
#886000
b110110011000110111000001 2
1)
b1011000 (
b1011000 +
1&
b110110011000110111000000 ,
b1001000000101000 %
b1001000000101000 *
17
b1011000 8
b1001000000101000 4
b101000 =
b101000 ;
#890000
0$
#895000
1$
#896000
0)
#900000
0$
#905000
1$
#906000
b1111111 3
b11011101 2
1)
b1010 (
b1010 +
b11011100 ,
b10110 %
b10110 *
b1111111 5
b1010 8
b10110 4
b101001 =
b101001 ;
#910000
0$
#915000
b1111111 #
b1111111 1
1$
#916000
0)
#920000
0$
#925000
1$
#926000
b11101100101011011001 2
1)
b1111100 (
b1111100 +
b11101100101011011000 ,
b1111010001010 %
b1111010001010 *
b1111100 8
b1111010001010 4
b101010 =
b101010 ;
#930000
0$
#935000
1$
#936000
0)
#940000
0$
#945000
1$
#946000
b111111111111111110000000 3
b111001000011011101011101 2
1)
b11010111 (
b11010111 +
0&
b111001000011011101011101 ,
b1101111011101011 %
b1101111011101011 *
b10000000 5
07
b11010111 8
b1101111011101011 4
b101011 =
b101011 ;
#950000
0$
#955000
b10000000 #
b10000000 1
1$
#956000
0)
#960000
0$
#965000
1$
#966000
b1111111 3
b1000001011000010 2
1)
b111 (
b111 +
b1000001011000010 ,
b1001010101110 %
b1001010101110 *
b1111111 5
b111 8
b1001010101110 4
b101100 =
b101100 ;
#970000
0$
#975000
b1111111 #
b1111111 1
1$
#976000
0)
#980000
0$
#985000
1$
#986000
b111111111111111110000000 3
b101100001111001011101010 2
1)
b11111001 (
b11111001 +
b101100001111001011101010 ,
b1010111010111010 %
b1010111010111010 *
b10000000 5
b11111001 8
b1010111010111010 4
b101101 =
b101101 ;
#990000
0$
#995000
b10000000 #
b10000000 1
1$
#996000
0)
#1000000
0$
#1005000
1$
#1006000
b111111111011001111110010 2
1)
b1010 (
b1010 +
b111111111011001111110010 ,
b1111100001100101 %
b1111100001100101 *
b1010 8
b1111100001100101 4
b101110 =
b101110 ;
#1010000
0$
#1015000
1$
#1016000
0)
#1020000
0$
#1025000
1$
#1026000
b1111111 3
b11000001101111011011110 2
1)
b11100011 (
b11100011 +
1&
b11000001101111011011101 ,
b110110100111111 %
b110110100111111 *
b1111111 5
17
b11100011 8
b110110100111111 4
b101111 =
b101111 ;
#1030000
0$
#1035000
b1111111 #
b1111111 1
1$
#1036000
0)
#1040000
0$
#1045000
1$
#1046000
b10010010010010010111 2
1)
b11110 (
b11110 +
b10010010010010010110 ,
b100111000000101 %
b100111000000101 *
b11110 8
b100111000000101 4
b110000 =
b110000 ;
#1050000
0$
#1055000
1$
#1056000
0)
#1060000
0$
#1065000
1$
#1066000
b10000011110000101011111 2
1)
b11101010 (
b11101010 +
b10000011110000101011110 ,
b100100000010011 %
b100100000010011 *
b11101010 8
b100100000010011 4
b110001 =
b110001 ;
#1070000
0$
#1075000
1$
#1076000
0)
#1080000
0$
#1085000
1$
#1086000
b111111111111111110000000 3
b111110000110000100110000 2
1)
b110001 (
b110001 +
0&
b111110000110000100110000 ,
b1101100000110000 %
b1101100000110000 *
b10000000 5
07
b110001 8
b1101100000110000 4
b110010 =
b110010 ;
#1090000
0$
#1095000
b10000000 #
b10000000 1
1$
#1096000
0)
#1100000
0$
#1105000
1$
#1106000
b1111111 3
b10000011001011111011 2
1)
b111001 (
b111001 +
b10000011001011111011 ,
b10010011010011 %
b10010011010011 *
b1111111 5
b111001 8
b10010011010011 4
b110011 =
b110011 ;
#1110000
0$
#1115000
b1111111 #
b1111111 1
1$
#1116000
0)
#1120000
0$
#1125000
1$
#1126000
b10000110111010101010 2
1)
b1000010 (
b1000010 +
b10000110111010101010 ,
b10000010110101 %
b10000010110101 *
b1000010 8
b10000010110101 4
b110100 =
b110100 ;
#1130000
0$
#1135000
1$
#1136000
0)
#1140000
0$
#1145000
1$
#1146000
b111111111111111110000000 3
b111010010010100010111110 2
1)
b11101010 (
b11101010 +
b111010010010100010111110 ,
b1110011100000011 %
b1110011100000011 *
b10000000 5
b11101010 8
b1110011100000011 4
b110101 =
b110101 ;
#1150000
0$
#1155000
b10000000 #
b10000000 1
1$
#1156000
0)
#1160000
0$
#1165000
1$
#1166000
b1111111 3
b1110110101010101 2
1)
b10110111 (
b10110111 +
1&
b1110110101010100 ,
b101001100 %
b101001100 *
b1111111 5
17
b10110111 8
b101001100 4
b110110 =
b110110 ;
#1170000
0$
#1175000
b1111111 #
b1111111 1
1$
#1176000
0)
#1180000
0$
#1185000
1$
#1186000
b10010010100001011111110 2
1)
b11100011 (
b11100011 +
b10010010100001011111101 ,
b101001010011111 %
b101001010011111 *
b11100011 8
b101001010011111 4
b110111 =
b110111 ;
#1190000
0$
#1195000
1$
#1196000
0)
#1200000
0$
#1205000
1$
#1206000
b111111111111111110000000 3
b110100101011011101100001 2
1)
b10110000 (
b10110000 +
b110100101011011101100000 ,
b1011111000100010 %
b1011111000100010 *
b10000000 5
b10110000 8
b1011111000100010 4
b111000 =
b111000 ;
#1210000
0$
#1215000
b10000000 #
b10000000 1
1$
#1216000
0)
#1220000
0$
#1225000
1$
#1226000
b1111111 3
b10101010101111100000 2
1)
b11101011 (
b11101011 +
0&
b10101010101111100000 ,
b101110100000 %
b101110100000 *
b1111111 5
07
b11101011 8
b101110100000 4
b111001 =
b111001 ;
#1230000
0$
#1235000
b1111111 #
b1111111 1
1$
#1236000
0)
#1240000
0$
#1245000
1$
#1246000
b100000100001001100111 2
1)
b10101111 (
b10101111 +
b100000100001001100111 ,
b1011111001001 %
b1011111001001 *
b10101111 8
b1011111001001 4
b111010 =
b111010 ;
#1250000
0$
#1255000
1$
#1256000
0)
#1260000
0$
#1265000
1$
#1266000
b111111111111111110000000 3
b111111100101101110111010 2
1)
b11101 (
b11101 +
b111111100101101110111010 ,
b1111000110000010 %
b1111000110000010 *
b10000000 5
b11101 8
b1111000110000010 4
b111011 =
b111011 ;
#1270000
0$
#1275000
b10000000 #
b10000000 1
1$
#1276000
0)
#1280000
0$
#1285000
1$
#1286000
b110110110111010010001000 2
1)
b11001000 (
b11001000 +
b110110110111010010001000 ,
b1101000100111001 %
b1101000100111001 *
b11001000 8
b1101000100111001 4
b111100 =
b111100 ;
#1290000
0$
#1295000
1$
#1296000
0)
#1300000
0$
#1305000
1$
#1306000
b111101001010011010010001 2
1)
b11100101 (
b11100101 +
1&
b111101001010011010010000 ,
b1111001101010000 %
b1111001101010000 *
17
b11100101 8
b1111001101010000 4
b111101 =
b111101 ;
#1310000
0$
#1315000
1$
#1316000
0)
#1320000
0$
#1325000
1$
#1326000
b110110011000100111001011 2
1)
b11010010 (
b11010010 +
b110110011000100111001010 ,
b1101000100011101 %
b1101000100011101 *
b11010010 8
b1101000100011101 4
b111110 =
b111110 ;
#1330000
0$
#1335000
1$
#1336000
0)
#1340000
0$
#1345000
1$
#1346000
b110111000100010000000001 2
1)
b10000011 (
b10000011 +
0&
b110111000100010000000001 ,
b1011101000101011 %
b1011101000101011 *
07
b10000011 8
b1011101000101011 4
b111111 =
b111111 ;
#1350000
0$
#1355000
1$
#1356000
0)
#1360000
0$
#1365000
1$
#1366000
b101111111111110101100101 2
1)
b11100100 (
b11100100 +
1&
b101111111111110101100100 ,
b1011100000100001 %
b1011100000100001 *
17
b11100100 8
b1011100000100001 4
b1000000 =
b1000000 ;
#1370000
0$
#1375000
1$
#1376000
0)
#1380000
0$
#1385000
1$
#1386000
b111100111100001101110110 2
1)
b11110 (
b11110 +
0&
b111100111100001101110110 ,
b1001011110010101 %
b1001011110010101 *
07
b11110 8
b1001011110010101 4
b1000001 =
b1000001 ;
#1390000
0$
#1395000
1$
#1396000
0)
#1400000
0$
#1405000
1$
#1406000
b111100111111011101101001 2
1)
b110100 (
b110100 +
1&
b111100111111011101101000 ,
b1100010011000010 %
b1100010011000010 *
17
b110100 8
b1100010011000010 4
b1000010 =
b1000010 ;
#1410000
0$
#1415000
1$
#1416000
0)
#1420000
0$
#1425000
1$
#1426000
b1111111 3
b1101000110001000000 2
1)
b1111000 (
b1111000 +
0&
b1101000110001000000 ,
b110111111000 %
b110111111000 *
b1111111 5
07
b1111000 8
b110111111000 4
b1000011 =
b1000011 ;
#1430000
0$
#1435000
b1111111 #
b1111111 1
1$
#1436000
0)
#1440000
0$
#1445000
1$
#1446000
b1110111011001100100000 2
1)
b11110000 (
b11110000 +
b1110111011001100100000 ,
b11111110101110 %
b11111110101110 *
b11110000 8
b11111110101110 4
b1000100 =
b1000100 ;
#1450000
0$
#1455000
1$
#1456000
0)
#1460000
0$
#1465000
1$
#1466000
b10001110101110111101000 2
1)
b10111000 (
b10111000 +
b10001110101110111101000 ,
b110001101001011 %
b110001101001011 *
b10111000 8
b110001101001011 4
b1000101 =
b1000101 ;
#1470000
0$
#1475000
1$
#1476000
0)
#1480000
0$
#1485000
1$
#1486000
b111111111111111110000000 3
b110110011001000111011111 2
1)
b11011111 (
b11011111 +
1&
b110110011001000111011110 ,
b1101001111100010 %
b1101001111100010 *
b10000000 5
17
b11011111 8
b1101001111100010 4
b1000110 =
b1000110 ;
#1490000
0$
#1495000
b10000000 #
b10000000 1
1$
#1496000
0)
#1500000
0$
#1505000
1$
#1506000
b110111010001101010010001 2
1)
b1010000 (
b1010000 +
b110111010001101010010000 ,
b1001000001010101 %
b1001000001010101 *
b1010000 8
b1001000001010101 4
b1000111 =
b1000111 ;
#1510000
0$
#1515000
1$
#1516000
0)
#1520000
0$
#1525000
1$
#1526000
b1111111 3
b1010001010011000110001 2
1)
b1010101 (
b1010101 +
0&
b1010001010011000110001 ,
b111101001101101 %
b111101001101101 *
b1111111 5
07
b1010101 8
b111101001101101 4
b1001000 =
b1001000 ;
#1530000
0$
#1535000
b1111111 #
b1111111 1
1$
#1536000
0)
#1540000
0$
#1545000
1$
#1546000
b110010001010000001010 2
1)
b1000110 (
b1000110 +
b110010001010000001010 ,
b101101110110111 %
b101101110110111 *
b1000110 8
b101101110110111 4
b1001001 =
b1001001 ;
#1550000
0$
#1555000
1$
#1556000
0)
#1560000
0$
#1565000
1$
#1566000
b101101110110011011001 2
1)
b10101000 (
b10101000 +
1&
b101101110110011011000 ,
b10001011101111 %
b10001011101111 *
17
b10101000 8
b10001011101111 4
b1001010 =
b1001010 ;
#1570000
0$
#1575000
1$
#1576000
0)
#1580000
0$
#1585000
1$
#1586000
b11010001101010110 2
1)
b101 (
b101 +
0&
b11010001101010110 ,
b101001111011110 %
b101001111011110 *
07
b101 8
b101001111011110 4
b1001011 =
b1001011 ;
#1590000
0$
#1595000
1$
#1596000
0)
#1600000
0$
#1605000
1$
#1606000
b100101100001000011100 2
1)
b1010100 (
b1010100 +
b100101100001000011100 ,
b11100100101011 %
b11100100101011 *
b1010100 8
b11100100101011 4
b1001100 =
b1001100 ;
#1610000
0$
#1615000
1$
#1616000
0)
#1620000
0$
#1625000
1$
#1626000
b111111111111111110000000 3
b110111011001110111110001 2
1)
b10011010 (
b10011010 +
1&
b110111011001110111110000 ,
b1100011011011000 %
b1100011011011000 *
b10000000 5
17
b10011010 8
b1100011011011000 4
b1001101 =
b1001101 ;
#1630000
0$
#1635000
b10000000 #
b10000000 1
1$
#1636000
0)
#1640000
0$
#1645000
1$
#1646000
b1111111 3
b1010011000101101110000 2
1)
b10100001 (
b10100001 +
b1010011000101101101111 ,
b100001000001111 %
b100001000001111 *
b1111111 5
b10100001 8
b100001000001111 4
b1001110 =
b1001110 ;
#1650000
0$
#1655000
b1111111 #
b1111111 1
1$
#1656000
0)
#1660000
0$
#1665000
1$
