rung2-quantizer/rtl/quantizer.sv
module quantizer #(
parameter int INPUT_WIDTH = 16,
parameter int OUTPUT_WIDTH = 8

)
(
    input logic clk,
    input logic rst_n,
    input logic valid_in,
    input logic signed [INPUT_WIDTH-1:0] data_in,
    input logic [7:0] scale,
    input logic round_mode,
    output logic signed [OUTPUT_WIDTH-1:0] data_out,
    output logic valid_out,
    output logic overflow

);

// internal signals
    logic signed [23:0] scaled;
    logic signed [23:0] rounded;
    logic signed [23:0] saturated;

    // stage 1 — scale
    assign scaled = data_in * $signed({1'b0, scale});

    //stage 2 - round
    always_comb begin
        if(round_mode == 1'b0)
            rounded = scaled;
        else 
            rounded = scaled + 24'sh1;
    end

    // stage 3 — saturate
    localparam signed [23:0] MAX_VAL = (2**(OUTPUT_WIDTH-1)) - 1;
    localparam signed [23:0] MIN_VAL = -(2**(OUTPUT_WIDTH-1));

    always_comb begin
        if (rounded > MAX_VAL) begin
            saturated = MAX_VAL;
            overflow  = 1'b1;
        end else if (rounded < MIN_VAL) begin
            saturated = MIN_VAL;
            overflow  = 1'b1;
        end else begin
            saturated = rounded;
            overflow  = 1'b0;
        end
    end

    // stage 4 — register output
    always_ff @(posedge clk or negedge rst_n) begin
        if (!rst_n) begin
            data_out  <= '0;
            valid_out <= 1'b0;
        end else if (valid_in) begin
            data_out  <= saturated[OUTPUT_WIDTH-1:0];
            valid_out <= 1'b1;
        end
    end

    endmodule

rung2-quantizer/tb/quantizer_tb.sv
`timescale 1ns/1ps

module quantizer_tb;
    logic clk;
    logic rst_n;
    logic valid_in;
    logic signed [15:0] data_in;
    logic [7:0] scale;
    logic round_mode;
    logic signed [7:0] data_out;
    logic valid_out;
    logic overflow;


quantizer #(.INPUT_WIDTH(16), .OUTPUT_WIDTH(8)) dut (.*);
always #5 clk = ~clk;

task automatic send(input signed [15:0] data_in_tb, input round_mode_tb, input [7:0] scale_tb);
    data_in= data_in_tb; round_mode = round_mode_tb; scale = scale_tb; valid_in = 1;
    @(posedge clk); #1;
    valid_in = 0;
endtask

task automatic check(input signed [7:0] expected, input expected_overflow, input string label);
    @(posedge clk); #1;
    if(data_out !== expected || overflow !== expected_overflow)
        $display("FAIL [%s]: got %0d expected %0d", label, data_out, expected);
    else
        $display("PASS [%s]: data_out = %0d", label, data_out);
endtask

initial begin
    $dumpfile("sim/waves.vcd");
    $dumpvars(0, quantizer_tb);

    clk = 0; rst_n = 0; valid_in = 0;
    data_in = 0; scale = 0; round_mode = 0;
    @(posedge clk); #1;
    rst_n = 1;

    //test 1
    send(5,0,3);
    check(15,0, "normal quantizer");
     // Test 2: clear works
     @(posedge clk); #1; 
    send(32767, 0, 255);
    check(127,1, "max saturation");

        // Test 3: negative input -4*3 = -12
     @(posedge clk); #1;
    send(-30, 0,3);
    check(-90,0, "negative input");

        // Test 4: max negative -128*-128 = 16384
     @(posedge clk); #1; 
    send(10, 1,3);
    check(31,0, "rounding check");

        $display("\nAll tests done.");
    $finish;
end


endmodule

rung2-quantizer/sim/waves.vcd
$date
	Wed May 27 14:52:19 2026
$end
$version
	Icarus Verilog
$end
$timescale
	1ps
$end
$scope module quantizer_tb $end
$var wire 1 ! valid_out $end
$var wire 1 " overflow $end
$var wire 8 # data_out [7:0] $end
$var reg 1 $ clk $end
$var reg 16 % data_in [15:0] $end
$var reg 1 & round_mode $end
$var reg 1 ' rst_n $end
$var reg 8 ( scale [7:0] $end
$var reg 1 ) valid_in $end
$scope module dut $end
$var wire 1 $ clk $end
$var wire 16 * data_in [15:0] $end
$var wire 1 & round_mode $end
$var wire 1 ' rst_n $end
$var wire 8 + scale [7:0] $end
$var wire 1 ) valid_in $end
$var wire 24 , scaled [23:0] $end
$var parameter 32 - INPUT_WIDTH $end
$var parameter 24 . MAX_VAL $end
$var parameter 24 / MIN_VAL $end
$var parameter 32 0 OUTPUT_WIDTH $end
$var reg 8 1 data_out [7:0] $end
$var reg 1 " overflow $end
$var reg 24 2 rounded [23:0] $end
$var reg 24 3 saturated [23:0] $end
$var reg 1 ! valid_out $end
$upscope $end
$scope task check $end
$upscope $end
$scope task send $end
$upscope $end
$upscope $end
$enddefinitions $end
$comment Show the parameter values. $end
$dumpall
b1000 0
b111111111111111110000000 /
b1111111 .
b10000 -
$end
#0
$dumpvars
b0 3
b0 2
b0 1
b0 ,
b0 +
b0 *
0)
b0 (
0'
0&
b0 %
0$
b0 #
0"
0!
$end
#5000
1$
#6000
b1111 3
b1111 2
1)
b1111 ,
b11 (
b11 +
b101 %
b101 *
1'
#10000
0$
#15000
1!
b1111 #
b1111 1
1$
#16000
0)
#20000
0$
#25000
1$
#30000
0$
#35000
1$
#36000
1"
b1111111 3
b11111110111111100000001 2
1)
b11111111 (
b11111111 +
b11111110111111100000001 ,
b111111111111111 %
b111111111111111 *
#40000
0$
#45000
b1111111 #
b1111111 1
1$
#46000
0)
#50000
0$
#55000
1$
#60000
0$
#65000
1$
#66000
0"
b111111111111111110100110 3
b111111111111111110100110 2
1)
b11 (
b11 +
b111111111111111110100110 ,
b1111111111100010 %
b1111111111100010 *
#70000
0$
#75000
b10100110 #
b10100110 1
1$
#76000
0)
#80000
0$
#85000
1$
#90000
0$
#95000
1$
#96000
b11111 3
b11111 2
1)
1&
b11110 ,
b1010 %
b1010 *
#100000
0$
#105000
b11111 #
b11111 1
1$
#106000
0)
