rung1-mac-unit/rtl/mac_unit.sv
module mac_unit #(
    parameter int INPUT_WIDTH = 8,
    parameter int ACCUM_WIDTH = 32
)(
    input logic clk,
    input logic rst_n,
    input logic valid_in,
    input logic signed [INPUT_WIDTH-1:0] a,
    input logic signed [INPUT_WIDTH-1:0] b,
    input logic clear,
    output logic signed [ACCUM_WIDTH-1:0] accum_out,
    output logic valid_out
);

//internal signals
logic signed [INPUT_WIDTH*2-1:0] product;
logic signed [ACCUM_WIDTH-1:0] accum_reg;

assign product = a * b;

always_ff @(posedge clk or negedge rst_n) begin
    if(!rst_n) begin
        accum_reg <= '0;
        valid_out <= 1'b0;
    end else if (clear) begin
        accum_reg <= '0;
        valid_out <= 1'b0;
    end else if (valid_in) begin
        accum_reg <= accum_reg + ACCUM_WIDTH'(product);
        valid_out <= 1'b1;
    end
end

assign accum_out = accum_reg;
endmodule

rung1-mac-unit/tb/mac_unit_tb.sv
`timescale  1ns/1ps

module mac_unit_tb;
    logic clk,rst_n,valid_in,clear;
    logic signed [7:0] a,b;
    logic signed [31:0] accum_out;
    logic valid_out;

mac_unit #(.INPUT_WIDTH(8), .ACCUM_WIDTH(32)) dut (.*);
always #5 clk = ~clk;

task automatic send(input signed [7:0] in_a, in_b);
    a = in_a; b = in_b; valid_in = 1;
    @(posedge clk); #1;
    valid_in = 0;
endtask

task automatic check(input signed [31:0] expected, input string label);
    @(posedge clk); #1;
    if(accum_out !== expected)
        $display("FAIL [%s]: got %0d", label, accum_out);
    else
        $display("PASS [%s]: accum = %0d", label, accum_out);
endtask

initial begin
    $dumpfile("sim/waves.vcd");
    $dumpvars(0, mac_unit_tb);

    clk = 0; rst_n = 0; valid_in = 0;
    clear = 0; a = 0; b = 0;
    @(posedge clk); #1;
    rst_n = 1;

    //test 1
    send(3,4);
    send(2,5);
    check(22, "basic accumulation");
     // Test 2: clear works
    clear = 1; @(posedge clk); #1; clear = 0;
    send(1, 1);
    check(1, "after clear");

        // Test 3: negative input -4*3 = -12
    clear = 1; @(posedge clk); #1; clear = 0;
    send(-4, 3);
    check(-12, "negative input");

        // Test 4: max negative -128*-128 = 16384
    clear = 1; @(posedge clk); #1; clear = 0;
    send(-128, -128);
    check(16384, "max negative squared");

        // Test 5: accumulate 16 values of 2*3 = 96
    clear = 1; @(posedge clk); #1; clear = 0;
    repeat(16) send(2, 3);
    check(96, "16x accumulation");

    $display("\nAll tests done.");
    $finish;
end

endmodule

rung1-mac-unit/sim/waves.vcd
$date
	Fri May 22 16:45:22 2026
$end
$version
	Icarus Verilog
$end
$timescale
	1ps
$end
$scope module mac_unit_tb $end
$var wire 1 ! valid_out $end
$var wire 32 " accum_out [31:0] $end
$var reg 8 # a [7:0] $end
$var reg 8 $ b [7:0] $end
$var reg 1 % clear $end
$var reg 1 & clk $end
$var reg 1 ' rst_n $end
$var reg 1 ( valid_in $end
$scope module dut $end
$var wire 8 ) a [7:0] $end
$var wire 32 * accum_out [31:0] $end
$var wire 8 + b [7:0] $end
$var wire 1 % clear $end
$var wire 1 & clk $end
$var wire 1 ' rst_n $end
$var wire 1 ( valid_in $end
$var wire 16 , product [15:0] $end
$var parameter 32 - ACCUM_WIDTH $end
$var parameter 32 . INPUT_WIDTH $end
$var reg 32 / accum_reg [31:0] $end
$var reg 1 ! valid_out $end
$upscope $end
$scope task check $end
$upscope $end
$scope task send $end
$upscope $end
$upscope $end
$enddefinitions $end
$comment Show the parameter values. $end
$dumpall
b1000 .
b100000 -
$end
#0
$dumpvars
b0 /
b0 ,
b0 +
b0 *
b0 )
0(
0'
0&
0%
b0 $
b0 #
b0 "
0!
$end
#5000
1&
#6000
1(
b1100 ,
b100 $
b100 +
b11 #
b11 )
1'
#10000
0&
#15000
1!
b1100 "
b1100 *
b1100 /
1&
#16000
b101 $
b101 +
b1010 ,
b10 #
b10 )
1(
#20000
0&
#25000
b10110 "
b10110 *
b10110 /
1&
#26000
0(
#30000
0&
#35000
1&
#36000
1%
#40000
0&
#45000
0!
b0 "
b0 *
b0 /
1&
#46000
1(
b1 $
b1 +
b1 ,
b1 #
b1 )
0%
#50000
0&
#55000
1!
b1 "
b1 *
b1 /
1&
#56000
0(
#60000
0&
#65000
1&
#66000
1%
#70000
0&
#75000
0!
b0 "
b0 *
b0 /
1&
#76000
1(
b11 $
b11 +
b1111111111110100 ,
b11111100 #
b11111100 )
0%
#80000
0&
#85000
1!
b11111111111111111111111111110100 "
b11111111111111111111111111110100 *
b11111111111111111111111111110100 /
1&
#86000
0(
#90000
0&
#95000
1&
#96000
1%
#100000
0&
#105000
0!
b0 "
b0 *
b0 /
1&
#106000
1(
b10000000 $
b10000000 +
b100000000000000 ,
b10000000 #
b10000000 )
0%
#110000
0&
#115000
1!
b100000000000000 "
b100000000000000 *
b100000000000000 /
1&
#116000
0(
#120000
0&
#125000
1&
#126000
1%
#130000
0&
#135000
0!
b0 "
b0 *
b0 /
1&
#136000
1(
b11 $
b11 +
b110 ,
b10 #
b10 )
0%
#140000
0&
#145000
1!
b110 "
b110 *
b110 /
1&
#146000
1(
#150000
0&
#155000
b1100 "
b1100 *
b1100 /
1&
#156000
1(
#160000
0&
#165000
b10010 "
b10010 *
b10010 /
1&
#166000
1(
#170000
0&
#175000
b11000 "
b11000 *
b11000 /
1&
#176000
1(
#180000
0&
#185000
b11110 "
b11110 *
b11110 /
1&
#186000
1(
#190000
0&
#195000
b100100 "
b100100 *
b100100 /
1&
#196000
1(
#200000
0&
#205000
b101010 "
b101010 *
b101010 /
1&
#206000
1(
#210000
0&
#215000
b110000 "
b110000 *
b110000 /
1&
#216000
1(
#220000
0&
#225000
b110110 "
b110110 *
b110110 /
1&
#226000
1(
#230000
0&
#235000
b111100 "
b111100 *
b111100 /
1&
#236000
1(
#240000
0&
#245000
b1000010 "
b1000010 *
b1000010 /
1&
#246000
1(
#250000
0&
#255000
b1001000 "
b1001000 *
b1001000 /
1&
#256000
1(
#260000
0&
#265000
b1001110 "
b1001110 *
b1001110 /
1&
#266000
1(
#270000
0&
#275000
b1010100 "
b1010100 *
b1010100 /
1&
#276000
1(
#280000
0&
#285000
b1011010 "
b1011010 *
b1011010 /
1&
#286000
1(
#290000
0&
#295000
b1100000 "
b1100000 *
b1100000 /
1&
#296000
0(
