rung1-mac-unit/rtl/mac_unit.sv
module mac_unit #(
    parameter int INPUT_WIDTH = 8,
    parameter int ACCUM_WIDTH = 32
)(
    input logic clk,
    input logic rst_n,
    input logic valid_in,
    input logic signed [INPUT_WIDTH-1:0] a,
    input logic signed [INPUT_WIDTH-1:0] b,
    input logic clear,
    output logic signed [ACCUM_WIDTH-1:0] accum_out,
    output logic valid_out
);

//internal signals
logic signed [INPUT_WIDTH*2-1:0] product;
logic signed [ACCUM_WIDTH-1:0] accum_reg;

assign product = a * b;

always_ff @(posedge clk or negedge rst_n) begin
    if(!rst_n) begin
        accum_reg <= '0;
        valid_out <= 1'b0;
    end else if (clear) begin
        accum_reg <= '0;
        valid_out <= 1'b0;
    end else if (valid_in) begin
        accum_reg <= accum_reg + ACCUM_WIDTH'(product);
        valid_out <= 1'b1;
    end
end

assign accum_out = accum_reg;
endmodule

rung1-mac-unit/tb/mac_unit_tb.sv
`timescale  1ns/1ps

module mac_unit_tb;
    logic clk,rst_n,valid_in,clear;
    logic signed [7:0] a,b;
    logic signed [31:0] accum_out;
    logic valid_out;

mac_unit #(.INPUT_WIDTH(8), .ACCUM_WIDTH(32)) dut (.*);
always #5 clk = ~clk;

task automatic send(input signed [7:0] in_a, in_b);
    a = in_a; b = in_b; valid_in = 1;
    @(posedge clk); #1;
    valid_in = 0;
endtask

task automatic check(input signed [31:0] expected, input string label);
    @(posedge clk); #1;
    if(accum_out !== expected)
        $display("FAIL [%s]: got %0d", label, accum_out);
    else
        $display("PASS [%s]: accum = %0d", label, accum_out);
endtask

initial begin
    $dumpfile("sim/waves.vcd");
    $dumpvars(0, mac_unit_tb);

    clk = 0; rst_n = 0; valid_in = 0;
    clear = 0; a = 0; b = 0;
    @(posedge clk); #1;
    rst_n = 1;

    //test 1
    send(3,4);
    send(2,5);
    check(22, "basic accumulation");
     // Test 2: clear works
    clear = 1; @(posedge clk); #1; clear = 0;
    send(1, 1);
    check(1, "after clear");

        // Test 3: negative input -4*3 = -12
    clear = 1; @(posedge clk); #1; clear = 0;
    send(-4, 3);
    check(-12, "negative input");

        // Test 4: max negative -128*-128 = 16384
    clear = 1; @(posedge clk); #1; clear = 0;
    send(-128, -128);
    check(16384, "max negative squared");

        // Test 5: accumulate 16 values of 2*3 = 96
    clear = 1; @(posedge clk); #1; clear = 0;
    repeat(16) send(2, 3);
    check(96, "16x accumulation");

    

    // Test 6: overflow check - 128 accumulations of 127*127 = 2,064,512
        clear = 1; @(posedge clk); #1; clear = 0;
        repeat(128) send(127, 127);
        check(2064512, "overflow check");

        $display("\nAll tests done.");
    $finish;
end

endmodule

rung1-mac-unit/sim/waves.vcd
$date
	Fri May 22 17:03:03 2026
$end
$version
	Icarus Verilog
$end
$timescale
	1ps
$end
$scope module mac_unit_tb $end
$var wire 1 ! valid_out $end
$var wire 32 " accum_out [31:0] $end
$var reg 8 # a [7:0] $end
$var reg 8 $ b [7:0] $end
$var reg 1 % clear $end
$var reg 1 & clk $end
$var reg 1 ' rst_n $end
$var reg 1 ( valid_in $end
$scope module dut $end
$var wire 8 ) a [7:0] $end
$var wire 32 * accum_out [31:0] $end
$var wire 8 + b [7:0] $end
$var wire 1 % clear $end
$var wire 1 & clk $end
$var wire 1 ' rst_n $end
$var wire 1 ( valid_in $end
$var wire 16 , product [15:0] $end
$var parameter 32 - ACCUM_WIDTH $end
$var parameter 32 . INPUT_WIDTH $end
$var reg 32 / accum_reg [31:0] $end
$var reg 1 ! valid_out $end
$upscope $end
$scope task check $end
$upscope $end
$scope task send $end
$upscope $end
$upscope $end
$enddefinitions $end
$comment Show the parameter values. $end
$dumpall
b1000 .
b100000 -
$end
#0
$dumpvars
b0 /
b0 ,
b0 +
b0 *
b0 )
0(
0'
0&
0%
b0 $
b0 #
b0 "
0!
$end
#5000
1&
#6000
1(
b1100 ,
b100 $
b100 +
b11 #
b11 )
1'
#10000
0&
#15000
1!
b1100 "
b1100 *
b1100 /
1&
#16000
b101 $
b101 +
b1010 ,
b10 #
b10 )
1(
#20000
0&
#25000
b10110 "
b10110 *
b10110 /
1&
#26000
0(
#30000
0&
#35000
1&
#36000
1%
#40000
0&
#45000
0!
b0 "
b0 *
b0 /
1&
#46000
1(
b1 $
b1 +
b1 ,
b1 #
b1 )
0%
#50000
0&
#55000
1!
b1 "
b1 *
b1 /
1&
#56000
0(
#60000
0&
#65000
1&
#66000
1%
#70000
0&
#75000
0!
b0 "
b0 *
b0 /
1&
#76000
1(
b11 $
b11 +
b1111111111110100 ,
b11111100 #
b11111100 )
0%
#80000
0&
#85000
1!
b11111111111111111111111111110100 "
b11111111111111111111111111110100 *
b11111111111111111111111111110100 /
1&
#86000
0(
#90000
0&
#95000
1&
#96000
1%
#100000
0&
#105000
0!
b0 "
b0 *
b0 /
1&
#106000
1(
b10000000 $
b10000000 +
b100000000000000 ,
b10000000 #
b10000000 )
0%
#110000
0&
#115000
1!
b100000000000000 "
b100000000000000 *
b100000000000000 /
1&
#116000
0(
#120000
0&
#125000
1&
#126000
1%
#130000
0&
#135000
0!
b0 "
b0 *
b0 /
1&
#136000
1(
b11 $
b11 +
b110 ,
b10 #
b10 )
0%
#140000
0&
#145000
1!
b110 "
b110 *
b110 /
1&
#146000
1(
#150000
0&
#155000
b1100 "
b1100 *
b1100 /
1&
#156000
1(
#160000
0&
#165000
b10010 "
b10010 *
b10010 /
1&
#166000
1(
#170000
0&
#175000
b11000 "
b11000 *
b11000 /
1&
#176000
1(
#180000
0&
#185000
b11110 "
b11110 *
b11110 /
1&
#186000
1(
#190000
0&
#195000
b100100 "
b100100 *
b100100 /
1&
#196000
1(
#200000
0&
#205000
b101010 "
b101010 *
b101010 /
1&
#206000
1(
#210000
0&
#215000
b110000 "
b110000 *
b110000 /
1&
#216000
1(
#220000
0&
#225000
b110110 "
b110110 *
b110110 /
1&
#226000
1(
#230000
0&
#235000
b111100 "
b111100 *
b111100 /
1&
#236000
1(
#240000
0&
#245000
b1000010 "
b1000010 *
b1000010 /
1&
#246000
1(
#250000
0&
#255000
b1001000 "
b1001000 *
b1001000 /
1&
#256000
1(
#260000
0&
#265000
b1001110 "
b1001110 *
b1001110 /
1&
#266000
1(
#270000
0&
#275000
b1010100 "
b1010100 *
b1010100 /
1&
#276000
1(
#280000
0&
#285000
b1011010 "
b1011010 *
b1011010 /
1&
#286000
1(
#290000
0&
#295000
b1100000 "
b1100000 *
b1100000 /
1&
#296000
0(
#300000
0&
#305000
1&
#306000
1%
#310000
0&
#315000
0!
b0 "
b0 *
b0 /
1&
#316000
1(
b1111111 $
b1111111 +
b11111100000001 ,
b1111111 #
b1111111 )
0%
#320000
0&
#325000
1!
b11111100000001 "
b11111100000001 *
b11111100000001 /
1&
#326000
1(
#330000
0&
#335000
b111111000000010 "
b111111000000010 *
b111111000000010 /
1&
#336000
1(
#340000
0&
#345000
b1011110100000011 "
b1011110100000011 *
b1011110100000011 /
1&
#346000
1(
#350000
0&
#355000
b1111110000000100 "
b1111110000000100 *
b1111110000000100 /
1&
#356000
1(
#360000
0&
#365000
b10011101100000101 "
b10011101100000101 *
b10011101100000101 /
1&
#366000
1(
#370000
0&
#375000
b10111101000000110 "
b10111101000000110 *
b10111101000000110 /
1&
#376000
1(
#380000
0&
#385000
b11011100100000111 "
b11011100100000111 *
b11011100100000111 /
1&
#386000
1(
#390000
0&
#395000
b11111100000001000 "
b11111100000001000 *
b11111100000001000 /
1&
#396000
1(
#400000
0&
#405000
b100011011100001001 "
b100011011100001001 *
b100011011100001001 /
1&
#406000
1(
#410000
0&
#415000
b100111011000001010 "
b100111011000001010 *
b100111011000001010 /
1&
#416000
1(
#420000
0&
#425000
b101011010100001011 "
b101011010100001011 *
b101011010100001011 /
1&
#426000
1(
#430000
0&
#435000
b101111010000001100 "
b101111010000001100 *
b101111010000001100 /
1&
#436000
1(
#440000
0&
#445000
b110011001100001101 "
b110011001100001101 *
b110011001100001101 /
1&
#446000
1(
#450000
0&
#455000
b110111001000001110 "
b110111001000001110 *
b110111001000001110 /
1&
#456000
1(
#460000
0&
#465000
b111011000100001111 "
b111011000100001111 *
b111011000100001111 /
1&
#466000
1(
#470000
0&
#475000
b111111000000010000 "
b111111000000010000 *
b111111000000010000 /
1&
#476000
1(
#480000
0&
#485000
b1000010111100010001 "
b1000010111100010001 *
b1000010111100010001 /
1&
#486000
1(
#490000
0&
#495000
b1000110111000010010 "
b1000110111000010010 *
b1000110111000010010 /
1&
#496000
1(
#500000
0&
#505000
b1001010110100010011 "
b1001010110100010011 *
b1001010110100010011 /
1&
#506000
1(
#510000
0&
#515000
b1001110110000010100 "
b1001110110000010100 *
b1001110110000010100 /
1&
#516000
1(
#520000
0&
#525000
b1010010101100010101 "
b1010010101100010101 *
b1010010101100010101 /
1&
#526000
1(
#530000
0&
#535000
b1010110101000010110 "
b1010110101000010110 *
b1010110101000010110 /
1&
#536000
1(
#540000
0&
#545000
b1011010100100010111 "
b1011010100100010111 *
b1011010100100010111 /
1&
#546000
1(
#550000
0&
#555000
b1011110100000011000 "
b1011110100000011000 *
b1011110100000011000 /
1&
#556000
1(
#560000
0&
#565000
b1100010011100011001 "
b1100010011100011001 *
b1100010011100011001 /
1&
#566000
1(
#570000
0&
#575000
b1100110011000011010 "
b1100110011000011010 *
b1100110011000011010 /
1&
#576000
1(
#580000
0&
#585000
b1101010010100011011 "
b1101010010100011011 *
b1101010010100011011 /
1&
#586000
1(
#590000
0&
#595000
b1101110010000011100 "
b1101110010000011100 *
b1101110010000011100 /
1&
#596000
1(
#600000
0&
#605000
b1110010001100011101 "
b1110010001100011101 *
b1110010001100011101 /
1&
#606000
1(
#610000
0&
#615000
b1110110001000011110 "
b1110110001000011110 *
b1110110001000011110 /
1&
#616000
1(
#620000
0&
#625000
b1111010000100011111 "
b1111010000100011111 *
b1111010000100011111 /
1&
#626000
1(
#630000
0&
#635000
b1111110000000100000 "
b1111110000000100000 *
b1111110000000100000 /
1&
#636000
1(
#640000
0&
#645000
b10000001111100100001 "
b10000001111100100001 *
b10000001111100100001 /
1&
#646000
1(
#650000
0&
#655000
b10000101111000100010 "
b10000101111000100010 *
b10000101111000100010 /
1&
#656000
1(
#660000
0&
#665000
b10001001110100100011 "
b10001001110100100011 *
b10001001110100100011 /
1&
#666000
1(
#670000
0&
#675000
b10001101110000100100 "
b10001101110000100100 *
b10001101110000100100 /
1&
#676000
1(
#680000
0&
#685000
b10010001101100100101 "
b10010001101100100101 *
b10010001101100100101 /
1&
#686000
1(
#690000
0&
#695000
b10010101101000100110 "
b10010101101000100110 *
b10010101101000100110 /
1&
#696000
1(
#700000
0&
#705000
b10011001100100100111 "
b10011001100100100111 *
b10011001100100100111 /
1&
#706000
1(
#710000
0&
#715000
b10011101100000101000 "
b10011101100000101000 *
b10011101100000101000 /
1&
#716000
1(
#720000
0&
#725000
b10100001011100101001 "
b10100001011100101001 *
b10100001011100101001 /
1&
#726000
1(
#730000
0&
#735000
b10100101011000101010 "
b10100101011000101010 *
b10100101011000101010 /
1&
#736000
1(
#740000
0&
#745000
b10101001010100101011 "
b10101001010100101011 *
b10101001010100101011 /
1&
#746000
1(
#750000
0&
#755000
b10101101010000101100 "
b10101101010000101100 *
b10101101010000101100 /
1&
#756000
1(
#760000
0&
#765000
b10110001001100101101 "
b10110001001100101101 *
b10110001001100101101 /
1&
#766000
1(
#770000
0&
#775000
b10110101001000101110 "
b10110101001000101110 *
b10110101001000101110 /
1&
#776000
1(
#780000
0&
#785000
b10111001000100101111 "
b10111001000100101111 *
b10111001000100101111 /
1&
#786000
1(
#790000
0&
#795000
b10111101000000110000 "
b10111101000000110000 *
b10111101000000110000 /
1&
#796000
1(
#800000
0&
#805000
b11000000111100110001 "
b11000000111100110001 *
b11000000111100110001 /
1&
#806000
1(
#810000
0&
#815000
b11000100111000110010 "
b11000100111000110010 *
b11000100111000110010 /
1&
#816000
1(
#820000
0&
#825000
b11001000110100110011 "
b11001000110100110011 *
b11001000110100110011 /
1&
#826000
1(
#830000
0&
#835000
b11001100110000110100 "
b11001100110000110100 *
b11001100110000110100 /
1&
#836000
1(
#840000
0&
#845000
b11010000101100110101 "
b11010000101100110101 *
b11010000101100110101 /
1&
#846000
1(
#850000
0&
#855000
b11010100101000110110 "
b11010100101000110110 *
b11010100101000110110 /
1&
#856000
1(
#860000
0&
#865000
b11011000100100110111 "
b11011000100100110111 *
b11011000100100110111 /
1&
#866000
1(
#870000
0&
#875000
b11011100100000111000 "
b11011100100000111000 *
b11011100100000111000 /
1&
#876000
1(
#880000
0&
#885000
b11100000011100111001 "
b11100000011100111001 *
b11100000011100111001 /
1&
#886000
1(
#890000
0&
#895000
b11100100011000111010 "
b11100100011000111010 *
b11100100011000111010 /
1&
#896000
1(
#900000
0&
#905000
b11101000010100111011 "
b11101000010100111011 *
b11101000010100111011 /
1&
#906000
1(
#910000
0&
#915000
b11101100010000111100 "
b11101100010000111100 *
b11101100010000111100 /
1&
#916000
1(
#920000
0&
#925000
b11110000001100111101 "
b11110000001100111101 *
b11110000001100111101 /
1&
#926000
1(
#930000
0&
#935000
b11110100001000111110 "
b11110100001000111110 *
b11110100001000111110 /
1&
#936000
1(
#940000
0&
#945000
b11111000000100111111 "
b11111000000100111111 *
b11111000000100111111 /
1&
#946000
1(
#950000
0&
#955000
b11111100000001000000 "
b11111100000001000000 *
b11111100000001000000 /
1&
#956000
1(
#960000
0&
#965000
b11111111111101000001 "
b11111111111101000001 *
b11111111111101000001 /
1&
#966000
1(
#970000
0&
#975000
b100000011111001000010 "
b100000011111001000010 *
b100000011111001000010 /
1&
#976000
1(
#980000
0&
#985000
b100000111110101000011 "
b100000111110101000011 *
b100000111110101000011 /
1&
#986000
1(
#990000
0&
#995000
b100001011110001000100 "
b100001011110001000100 *
b100001011110001000100 /
1&
#996000
1(
#1000000
0&
#1005000
b100001111101101000101 "
b100001111101101000101 *
b100001111101101000101 /
1&
#1006000
1(
#1010000
0&
#1015000
b100010011101001000110 "
b100010011101001000110 *
b100010011101001000110 /
1&
#1016000
1(
#1020000
0&
#1025000
b100010111100101000111 "
b100010111100101000111 *
b100010111100101000111 /
1&
#1026000
1(
#1030000
0&
#1035000
b100011011100001001000 "
b100011011100001001000 *
b100011011100001001000 /
1&
#1036000
1(
#1040000
0&
#1045000
b100011111011101001001 "
b100011111011101001001 *
b100011111011101001001 /
1&
#1046000
1(
#1050000
0&
#1055000
b100100011011001001010 "
b100100011011001001010 *
b100100011011001001010 /
1&
#1056000
1(
#1060000
0&
#1065000
b100100111010101001011 "
b100100111010101001011 *
b100100111010101001011 /
1&
#1066000
1(
#1070000
0&
#1075000
b100101011010001001100 "
b100101011010001001100 *
b100101011010001001100 /
1&
#1076000
1(
#1080000
0&
#1085000
b100101111001101001101 "
b100101111001101001101 *
b100101111001101001101 /
1&
#1086000
1(
#1090000
0&
#1095000
b100110011001001001110 "
b100110011001001001110 *
b100110011001001001110 /
1&
#1096000
1(
#1100000
0&
#1105000
b100110111000101001111 "
b100110111000101001111 *
b100110111000101001111 /
1&
#1106000
1(
#1110000
0&
#1115000
b100111011000001010000 "
b100111011000001010000 *
b100111011000001010000 /
1&
#1116000
1(
#1120000
0&
#1125000
b100111110111101010001 "
b100111110111101010001 *
b100111110111101010001 /
1&
#1126000
1(
#1130000
0&
#1135000
b101000010111001010010 "
b101000010111001010010 *
b101000010111001010010 /
1&
#1136000
1(
#1140000
0&
#1145000
b101000110110101010011 "
b101000110110101010011 *
b101000110110101010011 /
1&
#1146000
1(
#1150000
0&
#1155000
b101001010110001010100 "
b101001010110001010100 *
b101001010110001010100 /
1&
#1156000
1(
#1160000
0&
#1165000
b101001110101101010101 "
b101001110101101010101 *
b101001110101101010101 /
1&
#1166000
1(
#1170000
0&
#1175000
b101010010101001010110 "
b101010010101001010110 *
b101010010101001010110 /
1&
#1176000
1(
#1180000
0&
#1185000
b101010110100101010111 "
b101010110100101010111 *
b101010110100101010111 /
1&
#1186000
1(
#1190000
0&
#1195000
b101011010100001011000 "
b101011010100001011000 *
b101011010100001011000 /
1&
#1196000
1(
#1200000
0&
#1205000
b101011110011101011001 "
b101011110011101011001 *
b101011110011101011001 /
1&
#1206000
1(
#1210000
0&
#1215000
b101100010011001011010 "
b101100010011001011010 *
b101100010011001011010 /
1&
#1216000
1(
#1220000
0&
#1225000
b101100110010101011011 "
b101100110010101011011 *
b101100110010101011011 /
1&
#1226000
1(
#1230000
0&
#1235000
b101101010010001011100 "
b101101010010001011100 *
b101101010010001011100 /
1&
#1236000
1(
#1240000
0&
#1245000
b101101110001101011101 "
b101101110001101011101 *
b101101110001101011101 /
1&
#1246000
1(
#1250000
0&
#1255000
b101110010001001011110 "
b101110010001001011110 *
b101110010001001011110 /
1&
#1256000
1(
#1260000
0&
#1265000
b101110110000101011111 "
b101110110000101011111 *
b101110110000101011111 /
1&
#1266000
1(
#1270000
0&
#1275000
b101111010000001100000 "
b101111010000001100000 *
b101111010000001100000 /
1&
#1276000
1(
#1280000
0&
#1285000
b101111101111101100001 "
b101111101111101100001 *
b101111101111101100001 /
1&
#1286000
1(
#1290000
0&
#1295000
b110000001111001100010 "
b110000001111001100010 *
b110000001111001100010 /
1&
#1296000
1(
#1300000
0&
#1305000
b110000101110101100011 "
b110000101110101100011 *
b110000101110101100011 /
1&
#1306000
1(
#1310000
0&
#1315000
b110001001110001100100 "
b110001001110001100100 *
b110001001110001100100 /
1&
#1316000
1(
#1320000
0&
#1325000
b110001101101101100101 "
b110001101101101100101 *
b110001101101101100101 /
1&
#1326000
1(
#1330000
0&
#1335000
b110010001101001100110 "
b110010001101001100110 *
b110010001101001100110 /
1&
#1336000
1(
#1340000
0&
#1345000
b110010101100101100111 "
b110010101100101100111 *
b110010101100101100111 /
1&
#1346000
1(
#1350000
0&
#1355000
b110011001100001101000 "
b110011001100001101000 *
b110011001100001101000 /
1&
#1356000
1(
#1360000
0&
#1365000
b110011101011101101001 "
b110011101011101101001 *
b110011101011101101001 /
1&
#1366000
1(
#1370000
0&
#1375000
b110100001011001101010 "
b110100001011001101010 *
b110100001011001101010 /
1&
#1376000
1(
#1380000
0&
#1385000
b110100101010101101011 "
b110100101010101101011 *
b110100101010101101011 /
1&
#1386000
1(
#1390000
0&
#1395000
b110101001010001101100 "
b110101001010001101100 *
b110101001010001101100 /
1&
#1396000
1(
#1400000
0&
#1405000
b110101101001101101101 "
b110101101001101101101 *
b110101101001101101101 /
1&
#1406000
1(
#1410000
0&
#1415000
b110110001001001101110 "
b110110001001001101110 *
b110110001001001101110 /
1&
#1416000
1(
#1420000
0&
#1425000
b110110101000101101111 "
b110110101000101101111 *
b110110101000101101111 /
1&
#1426000
1(
#1430000
0&
#1435000
b110111001000001110000 "
b110111001000001110000 *
b110111001000001110000 /
1&
#1436000
1(
#1440000
0&
#1445000
b110111100111101110001 "
b110111100111101110001 *
b110111100111101110001 /
1&
#1446000
1(
#1450000
0&
#1455000
b111000000111001110010 "
b111000000111001110010 *
b111000000111001110010 /
1&
#1456000
1(
#1460000
0&
#1465000
b111000100110101110011 "
b111000100110101110011 *
b111000100110101110011 /
1&
#1466000
1(
#1470000
0&
#1475000
b111001000110001110100 "
b111001000110001110100 *
b111001000110001110100 /
1&
#1476000
1(
#1480000
0&
#1485000
b111001100101101110101 "
b111001100101101110101 *
b111001100101101110101 /
1&
#1486000
1(
#1490000
0&
#1495000
b111010000101001110110 "
b111010000101001110110 *
b111010000101001110110 /
1&
#1496000
1(
#1500000
0&
#1505000
b111010100100101110111 "
b111010100100101110111 *
b111010100100101110111 /
1&
#1506000
1(
#1510000
0&
#1515000
b111011000100001111000 "
b111011000100001111000 *
b111011000100001111000 /
1&
#1516000
1(
#1520000
0&
#1525000
b111011100011101111001 "
b111011100011101111001 *
b111011100011101111001 /
1&
#1526000
1(
#1530000
0&
#1535000
b111100000011001111010 "
b111100000011001111010 *
b111100000011001111010 /
1&
#1536000
1(
#1540000
0&
#1545000
b111100100010101111011 "
b111100100010101111011 *
b111100100010101111011 /
1&
#1546000
1(
#1550000
0&
#1555000
b111101000010001111100 "
b111101000010001111100 *
b111101000010001111100 /
1&
#1556000
1(
#1560000
0&
#1565000
b111101100001101111101 "
b111101100001101111101 *
b111101100001101111101 /
1&
#1566000
1(
#1570000
0&
#1575000
b111110000001001111110 "
b111110000001001111110 *
b111110000001001111110 /
1&
#1576000
1(
#1580000
0&
#1585000
b111110100000101111111 "
b111110100000101111111 *
b111110100000101111111 /
1&
#1586000
1(
#1590000
0&
#1595000
b111111000000010000000 "
b111111000000010000000 *
b111111000000010000000 /
1&
#1596000
0(
