rung4-gear-quantizer/rtl/gear_quantizer.sv
module gear_quantizer #(
    parameter int DATA_WIDTH = 8,
    parameter int INT4_WIDTH = 4
)(
    input logic signed [DATA_WIDTH-1:0] data_in,
    input logic  [INT4_WIDTH-1:0] scale,
    input logic valid_in,
    input logic [DATA_WIDTH-1:0] threshold,
    output logic signed [INT4_WIDTH-1:0] int4_out,
    output logic valid_out,
    output logic signed [DATA_WIDTH-1:0] sideband_out,
    output logic is_outlier,
    input logic clk,
    input logic rst_n,
    input logic round_mode
);

logic  [DATA_WIDTH-1:0] abs_data_in;
logic signed  [DATA_WIDTH + INT4_WIDTH - 1:0] mult_res;
logic signed  [DATA_WIDTH + INT4_WIDTH - 1:0] shifted_res;
logic signed  [DATA_WIDTH + INT4_WIDTH - 1:0] rounded_res;
logic signed  [1:0] round_incr;
logic round_bit;
logic signed  [INT4_WIDTH-1:0] post_clip_res;
logic outlier_comp_res;

// scale is interpreted as a fixed-point fraction scale/2^INT4_WIDTH (0 to 15/16),
// so it can only attenuate data_in, never amplify it
localparam int SHIFT_BITS = INT4_WIDTH;
localparam signed [INT4_WIDTH-1:0] INT4_MAX =  (1 << (INT4_WIDTH-1)) - 1;
localparam signed [INT4_WIDTH-1:0] INT4_MIN = -(1 << (INT4_WIDTH-1));

always_comb begin
    abs_data_in = (data_in[DATA_WIDTH-1]) ? -data_in : data_in;
    mult_res = data_in * $signed({1'b0, scale});
    shifted_res = mult_res >>> SHIFT_BITS;
    round_bit = mult_res[SHIFT_BITS-1];
    round_incr = (round_mode && round_bit) ? 2'sb01 : 2'sb00;
    rounded_res = shifted_res + round_incr;
    post_clip_res = (rounded_res > INT4_MAX) ? INT4_MAX : (rounded_res < INT4_MIN) ? INT4_MIN : rounded_res[INT4_WIDTH-1:0];
    outlier_comp_res = (abs_data_in > threshold);
end

always_ff @(posedge clk or negedge rst_n) begin
    if (!rst_n) begin
        int4_out <= '0;
        valid_out <= 1'b0;
        sideband_out <= '0;
        is_outlier <= 1'b0;
    end else begin
        valid_out <= valid_in;
        if (valid_in) begin
            int4_out <= outlier_comp_res ? '0 : post_clip_res;
            sideband_out <= outlier_comp_res ? data_in : '0;
            is_outlier <= outlier_comp_res;
        end
    end
end
endmodule

rung4-gear-quantizer/tb/tb_cosim.sv
`timescale 1ns/1ps
module tb_cosim;

    localparam int DATA_WIDTH = 8;
    localparam int INT4_WIDTH = 4;

    logic                         clk, rst_n, valid_in, valid_out;
    logic signed [DATA_WIDTH-1:0] data_in;
    logic        [DATA_WIDTH-1:0] threshold;
    logic        [INT4_WIDTH-1:0] scale;
    logic                         round_mode;
    logic signed [INT4_WIDTH-1:0] int4_out;
    logic signed [DATA_WIDTH-1:0] sideband_out;
    logic                         is_outlier;

    gear_quantizer #(.DATA_WIDTH(DATA_WIDTH), .INT4_WIDTH(INT4_WIDTH)) dut (.*);

    initial clk = 0;
    always #5 clk = ~clk;

    // expected values read from file
    logic signed [DATA_WIDTH-1:0] exp_sideband;
    logic signed [INT4_WIDTH-1:0] exp_int4;
    logic                         exp_outlier;
    logic                         vec_round_mode;

    int fd, passes, fails;

    initial begin
        $dumpfile("sim/waves_cosim.vcd");
        $dumpvars(0, tb_cosim);
        clk = 0; rst_n = 0; valid_in = 0; round_mode = 0;
        repeat(2) @(posedge clk);
        rst_n = 1;
        @(posedge clk); #1;

        passes = 0; fails = 0;
        fd = $fopen("sim/vectors.txt", "r");

        while (!$feof(fd)) begin
            if ($fscanf(fd, "%d %d %d %d %d %d %d\n",
                        data_in, threshold, scale, vec_round_mode,
                        exp_outlier, exp_int4, exp_sideband) == 7) begin
                // drive and check — what goes here?
                round_mode = vec_round_mode;
                valid_in = 1;
                @(posedge clk); #1;
                valid_in = 0;
                if (valid_out !== 1'b1) begin
                    $display("FAIL: valid_out not high");
                    fails++;
                end else if (is_outlier !== exp_outlier) begin
                    $display("FAIL: is_outlier got %0b exp %0b", is_outlier, exp_outlier);
                    fails++;
                end else if (exp_outlier && sideband_out !== exp_sideband) begin
                    $display("FAIL: sideband got %0d exp %0d", sideband_out, exp_sideband);
                    fails++;
                end else if (!exp_outlier && int4_out !== exp_int4) begin
                    $display("FAIL: int4_out got %0d exp %0d", int4_out, exp_int4);
                    fails++;
                end else begin
                    $display("PASS");
                    passes++;
                end           // closes else begin
            end               // closes if ($fscanf) begin
        end                   // closes while begin

        $fclose(fd);
        $display("\nCo-sim done: %0d/%0d passed", passes, passes+fails);
        $finish;
    end

endmodule

rung4-gear-quantizer/sim/waves_cosim.vcd
$date
	Sat Jul  4 12:54:53 2026
$end
$version
	Icarus Verilog
$end
$timescale
	1ps
$end
$scope module tb_cosim $end
$var wire 1 ! valid_out $end
$var wire 8 " sideband_out [7:0] $end
$var wire 1 # is_outlier $end
$var wire 4 $ int4_out [3:0] $end
$var parameter 32 % DATA_WIDTH $end
$var parameter 32 & INT4_WIDTH $end
$var reg 1 ' clk $end
$var reg 8 ( data_in [7:0] $end
$var reg 4 ) exp_int4 [3:0] $end
$var reg 1 * exp_outlier $end
$var reg 8 + exp_sideband [7:0] $end
$var reg 1 , round_mode $end
$var reg 1 - rst_n $end
$var reg 4 . scale [3:0] $end
$var reg 8 / threshold [7:0] $end
$var reg 1 0 valid_in $end
$var reg 1 1 vec_round_mode $end
$var integer 32 2 fails [31:0] $end
$var integer 32 3 fd [31:0] $end
$var integer 32 4 passes [31:0] $end
$scope module dut $end
$var wire 1 ' clk $end
$var wire 8 5 data_in [7:0] $end
$var wire 1 , round_mode $end
$var wire 1 - rst_n $end
$var wire 4 6 scale [3:0] $end
$var wire 8 7 threshold [7:0] $end
$var wire 1 0 valid_in $end
$var parameter 32 8 DATA_WIDTH $end
$var parameter 4 9 INT4_MAX $end
$var parameter 4 : INT4_MIN $end
$var parameter 32 ; INT4_WIDTH $end
$var parameter 32 < SHIFT_BITS $end
$var reg 8 = abs_data_in [7:0] $end
$var reg 4 > int4_out [3:0] $end
$var reg 1 # is_outlier $end
$var reg 12 ? mult_res [11:0] $end
$var reg 1 @ outlier_comp_res $end
$var reg 4 A post_clip_res [3:0] $end
$var reg 1 B round_bit $end
$var reg 2 C round_incr [1:0] $end
$var reg 12 D rounded_res [11:0] $end
$var reg 12 E shifted_res [11:0] $end
$var reg 8 F sideband_out [7:0] $end
$var reg 1 ! valid_out $end
$upscope $end
$upscope $end
$enddefinitions $end
$comment Show the parameter values. $end
$dumpall
b100 <
b100 ;
b1000 :
b111 9
b1000 8
b100 &
b1000 %
$end
#0
$dumpvars
b0 F
bx E
bx D
b0 C
xB
bx A
x@
bx ?
b0 >
bx =
bx 7
bx 6
bx 5
b0 4
b0 3
b0 2
x1
00
bx /
bx .
0-
0,
bx +
x*
bx )
bx (
0'
b0 $
0#
b0 "
0!
$end
#5000
1'
#10000
0'
#15000
1-
1'
#20000
0'
#25000
1'
#26000
1@
b111 A
b10010 D
1B
b10010 E
b100101001 ?
b1100011 =
10
b1100011 +
b0 )
1*
01
b11 .
b11 6
b110010 /
b110010 7
b1100011 (
b1100011 5
b10000000000000000000000000000011 3
#30000
0'
#35000
1#
b1100011 "
b1100011 F
1!
1'
#36000
b1001 D
0B
b1001 E
b10010011 ?
b110001 =
1,
b110001 +
11
b101001 /
b101001 7
b110001 (
b110001 5
b1 4
10
#40000
0'
#45000
b110001 "
b110001 F
1'
#46000
0@
b1000 A
b111111111000 D
1B
b111111111000 E
b111110001101 ?
b10111 =
0,
b0 +
b1000 )
0*
01
b101 .
b101 6
b1000111 /
b1000111 7
b11101001 (
b11101001 5
b10 4
10
#50000
0'
#55000
0#
b0 "
b0 F
b1000 $
b1000 >
1'
#56000
b0 A
b0 D
b0 E
b1010 ?
b1010 =
b0 )
b1 .
b1 6
b110111 /
b110111 7
b1010 (
b1010 5
b11 4
10
#60000
0'
#65000
b0 $
b0 >
1'
#66000
b100 A
b100 D
0B
b100 E
b1000100 ?
b100010 =
b100 )
b10 .
b10 6
b111101 /
b111101 7
b100010 (
b100010 5
b100 4
10
#70000
0'
#75000
b100 $
b100 >
1'
#76000
1@
b1000 A
b111111100111 D
b1 C
1B
b111111100110 E
b111001101010 ?
b111010 =
1,
b11000110 +
b0 )
1*
11
b111 .
b111 6
b101011 /
b101011 7
b11000110 (
b11000110 5
b101 4
10
#80000
0'
#85000
1#
b11000110 "
b11000110 F
b0 $
b0 >
1'
#86000
b111111110011 D
b111111110010 E
b111100101110 ?
b1110 =
b11110010 +
b1111 .
b1111 6
b1011 /
b1011 7
b11110010 (
b11110010 5
b110 4
10
#90000
0'
#95000
b11110010 "
b11110010 F
1'
#96000
0@
b11 A
b11 D
b0 C
0B
b11 E
b110000 ?
b100 =
b0 +
b11 )
0*
b1100 .
b1100 6
b101010 /
b101010 7
b100 (
b100 5
b111 4
10
#100000
0'
#105000
0#
b0 "
b0 F
b11 $
b11 >
1'
#106000
b111 A
b110111 D
b110111 E
b1101110101 ?
b111011 =
0,
b111 )
01
b1111 .
b1111 6
b1010100 /
b1010100 7
b111011 (
b111011 5
b1000 4
10
#110000
0'
#115000
b111 $
b111 >
1'
#116000
1@
b0 A
b0 D
b0 E
b0 ?
b1001000 =
b10111000 +
b0 )
1*
b0 .
b0 6
b111 /
b111 7
b10111000 (
b10111000 5
b1001 4
10
#120000
0'
#125000
1#
b10111000 "
b10111000 F
b0 $
b0 >
1'
#126000
b1000 A
b111111110010 D
b1 C
1B
b111111110001 E
b111100011111 ?
b101101 =
1,
b11010011 +
11
b101 .
b101 6
b100010 /
b100010 7
b11010011 (
b11010011 5
b1010 4
10
#130000
0'
#135000
b11010011 "
b11010011 F
1'
#136000
b111110100101 D
b0 C
b111110100101 E
b101001011101 ?
b1101111 =
0,
b10010001 +
01
b1101 .
b1101 6
b1100010 /
b1100010 7
b10010001 (
b10010001 5
b1011 4
10
#140000
0'
#145000
b10010001 "
b10010001 F
1'
#146000
0@
b1100 A
b111111111100 D
0B
b111111111100 E
b111111000110 ?
b11101 =
b0 +
b1100 )
0*
b10 .
b10 6
b100000 /
b100000 7
b11100011 (
b11100011 5
b1100 4
10
#150000
0'
#155000
0#
b0 "
b0 F
b1100 $
b1100 >
1'
#156000
1@
b1000 A
b111111100100 D
b111111100100 E
b111001000111 ?
b111111 =
b11000001 +
b0 )
1*
b111 .
b111 6
b11110 /
b11110 7
b11000001 (
b11000001 5
b1101 4
10
#160000
0'
#165000
1#
b11000001 "
b11000001 F
b0 $
b0 >
1'
#166000
b111 A
b111 D
b111 E
b1110010 ?
b111001 =
b111001 +
b10 .
b10 6
b110 /
b110 7
b111001 (
b111001 5
b1110 4
10
#170000
0'
#175000
b111001 "
b111001 F
1'
#176000
b1000 A
b111111011000 D
1B
b111111011000 E
b110110001101 ?
b11000111 +
b1011 .
b1011 6
b1000 /
b1000 7
b11000111 (
b11000111 5
b1111 4
10
#180000
0'
#185000
b11000111 "
b11000111 F
1'
#186000
b111 A
b1001011 D
0B
b1001011 E
b10010110000 ?
b1111000 =
1,
b1111000 +
11
b1010 .
b1010 6
b11000 /
b11000 7
b1111000 (
b1111000 5
b10000 4
10
#190000
0'
#195000
b1111000 "
b1111000 F
1'
#196000
0@
b1011 A
b111111111011 D
b1 C
1B
b111111111010 E
b111110101100 ?
b1100 =
b0 +
b1011 )
0*
b111 .
b111 6
b1001001 /
b1001001 7
b11110100 (
b11110100 5
b10001 4
10
#200000
0'
#205000
0#
b0 "
b0 F
b1011 $
b1011 >
1'
#206000
1@
b1000 A
b111111001101 D
b0 C
0B
b111111001101 E
b110011010110 ?
b1011010 =
b10100110 +
b0 )
1*
b1001 .
b1001 6
b110011 /
b110011 7
b10100110 (
b10100110 5
b10010 4
10
#210000
0'
#215000
1#
b10100110 "
b10100110 F
b0 $
b0 >
1'
#216000
b10 A
b10 D
b10 E
b100000 ?
b100000 =
b100000 +
b1 .
b1 6
b1100 /
b1100 7
b100000 (
b100000 5
b10011 4
10
#220000
0'
#225000
b100000 "
b100000 F
1'
#226000
b111 A
b1110 D
b1110 E
b11100100 ?
b100110 =
b100110 +
b110 .
b110 6
b10011 /
b10011 7
b100110 (
b100110 5
b10100 4
10
#230000
0'
#235000
b100110 "
b100110 F
1'
#236000
0@
b1000 A
b111111100110 D
b111111100110 E
b111001100000 ?
b110100 =
0,
b0 +
b1000 )
0*
01
b1000 .
b1000 6
b1001101 /
b1001101 7
b11001100 (
b11001100 5
b10101 4
10
#240000
0'
#245000
0#
b0 "
b0 F
b1000 $
b1000 >
1'
#246000
1@
b111 A
b1101000 D
b1101000 E
b11010000010 ?
b1110111 =
b1110111 +
b0 )
1*
b1110 .
b1110 6
b1011110 /
b1011110 7
b1110111 (
b1110111 5
b10110 4
10
#250000
0'
#255000
1#
b1110111 "
b1110111 F
b0 $
b0 >
1'
#256000
b1000 A
b111111100010 D
1B
b111111100010 E
b111000101000 ?
b1110110 =
b10001010 +
b100 .
b100 6
b110100 /
b110100 7
b10001010 (
b10001010 5
b10111 4
10
#260000
0'
#265000
b10001010 "
b10001010 F
1'
#266000
b111111110001 D
0B
b111111110001 E
b111100010000 ?
b1111000 =
b10001000 +
b10 .
b10 6
b101000 /
b101000 7
b10001000 (
b10001000 5
b11000 4
10
#270000
0'
#275000
b10001000 "
b10001000 F
1'
#276000
0@
b111111100011 D
b111111100011 E
b111000110000 ?
b111010 =
1,
b0 +
b1000 )
0*
11
b1000 .
b1000 6
b1010001 /
b1010001 7
b11000110 (
b11000110 5
b11001 4
10
#280000
0'
#285000
0#
b0 "
b0 F
b1000 $
b1000 >
1'
#286000
b111111110000 D
b111111110000 E
b111100000000 ?
b100000 =
b1011001 /
b1011001 7
b11100000 (
b11100000 5
b11010 4
10
#290000
0'
#295000
1'
#296000
b111111110111 D
b111111110111 E
b111101110001 ?
b1011 =
0,
01
b1101 .
b1101 6
b1011 /
b1011 7
b11110101 (
b11110101 5
b11011 4
10
#300000
0'
#305000
1'
#306000
1@
b0 A
b0 D
b0 E
b0 ?
b111100 =
1,
b11000100 +
b0 )
1*
11
b0 .
b0 6
b11111 /
b11111 7
b11000100 (
b11000100 5
b11100 4
10
#310000
0'
#315000
1#
b11000100 "
b11000100 F
b0 $
b0 >
1'
#316000
b111 A
b1010 D
b1010 E
b10100000 ?
b1010000 =
b1010000 +
b10 .
b10 6
b110100 /
b110100 7
b1010000 (
b1010000 5
b11101 4
10
#320000
0'
#325000
b1010000 "
b1010000 F
1'
#326000
b100101 D
b1 C
1B
b100100 E
b1001001001 ?
b1110101 =
b1110101 +
b101 .
b101 6
b1011011 /
b1011011 7
b1110101 (
b1110101 5
b11110 4
10
#330000
0'
#335000
b1110101 "
b1110101 F
1'
#336000
0@
b1110 D
b0 C
0B
b1110 E
b11100111 ?
b100001 =
0,
b0 +
b111 )
0*
01
b111 .
b111 6
b1000111 /
b1000111 7
b100001 (
b100001 5
b11111 4
10
#340000
0'
#345000
0#
b0 "
b0 F
b111 $
b111 >
1'
#346000
b10 A
b10 D
b10 E
b100100 ?
b10010 =
1,
b10 )
11
b10 .
b10 6
b10110 /
b10110 7
b10010 (
b10010 5
b100000 4
10
#350000
0'
#355000
b10 $
b10 >
1'
#356000
b111 A
b1000 D
1B
b1000 E
b10001100 ?
b1010 =
0,
b111 )
01
b1110 .
b1110 6
b11110 /
b11110 7
b1010 (
b1010 5
b100001 4
10
#360000
0'
#365000
b111 $
b111 >
1'
#366000
b1001 A
b111111111001 D
b111111111001 E
b111110011110 ?
b111 =
b1001 )
b110010 /
b110010 7
b11111001 (
b11111001 5
b100010 4
10
#370000
0'
#375000
b1001 $
b1001 >
1'
#376000
1@
b111 A
b1000111 D
0B
b1000111 E
b10001110100 ?
b1011111 =
1,
b1011111 +
b0 )
1*
11
b1100 .
b1100 6
b111011 /
b111011 7
b1011111 (
b1011111 5
b100011 4
10
#380000
0'
#385000
1#
b1011111 "
b1011111 F
b0 $
b0 >
1'
#386000
b1000 A
b111111010011 D
b111111010011 E
b110100110110 ?
b1110111 =
0,
b10001001 +
01
b110 .
b110 6
b11011 /
b11011 7
b10001001 (
b10001001 5
b100100 4
10
#390000
0'
#395000
b10001001 "
b10001001 F
1'
#396000
b111 A
b10111 D
b10111 E
b101110111 ?
b1001011 =
1,
b1001011 +
11
b101 .
b101 6
b100001 /
b100001 7
b1001011 (
b1001011 5
b100101 4
10
#400000
0'
#405000
b1001011 "
b1001011 F
1'
#406000
b111 D
1B
b111 E
b1111110 ?
b10010 =
0,
b10010 +
01
b111 .
b111 6
b1010 /
b1010 7
b10010 (
b10010 5
b100110 4
10
#410000
0'
#415000
b10010 "
b10010 F
1'
#416000
0@
b1000 A
b111111110000 D
0B
b111111110000 E
b111100000100 ?
b111111 =
b0 +
b1000 )
0*
b100 .
b100 6
b1000110 /
b1000110 7
b11000001 (
b11000001 5
b100111 4
10
#420000
0'
#425000
0#
b0 "
b0 F
b1000 $
b1000 >
1'
#426000
b111111101010 D
1B
b111111101010 E
b111010101000 ?
b1010110 =
b1011101 /
b1011101 7
b10101010 (
b10101010 5
b101000 4
10
#430000
0'
#435000
1'
#436000
1@
b111111110101 D
0B
b111111110101 E
b111101010100 ?
b10101010 +
b0 )
1*
b10 .
b10 6
b100101 /
b100101 7
b101001 4
10
#440000
0'
#445000
1#
b10101010 "
b10101010 F
b0 $
b0 >
1'
#446000
0@
b0 A
b0 D
b0 E
b0 ?
b0 =
b0 +
0*
b1011111 /
b1011111 7
b0 (
b0 5
b101010 4
10
#450000
0'
#455000
0#
b0 "
b0 F
1'
#456000
1@
b1000 A
b111111110101 D
b1 C
1B
b111111110100 E
b111101001010 ?
b1110 =
1,
b11110010 +
1*
11
b1101 .
b1101 6
b1010 /
b1010 7
b11110010 (
b11110010 5
b101011 4
10
#460000
0'
#465000
1#
b11110010 "
b11110010 F
1'
#466000
0@
b0 A
b0 D
b0 C
0B
b0 E
b0 ?
b10011 =
b0 +
0*
b0 .
b0 6
b100100 /
b100100 7
b11101101 (
b11101101 5
b101100 4
10
#470000
0'
#475000
0#
b0 "
b0 F
1'
#476000
1@
b1000 A
b111111000010 D
b111111000010 E
b110000100010 ?
b1100011 =
0,
b10011101 +
1*
01
b1010 .
b1010 6
b111011 /
b111011 7
b10011101 (
b10011101 5
b101101 4
10
#480000
0'
#485000
1#
b10011101 "
b10011101 F
1'
#486000
0@
b1101 A
b111111111101 D
b1 C
1B
b111111111100 E
b111111001010 ?
b10010 =
1,
b0 +
b1101 )
0*
11
b11 .
b11 6
b100010 /
b100010 7
b11101110 (
b11101110 5
b101110 4
10
#490000
0'
#495000
0#
b0 "
b0 F
b1101 $
b1101 >
1'
#496000
1@
b1000 A
b111111100011 D
b111111100010 E
b111000101100 ?
b100111 =
b11011001 +
b0 )
1*
b1100 .
b1100 6
b101 /
b101 7
b11011001 (
b11011001 5
b101111 4
10
#500000
0'
#505000
1#
b11011001 "
b11011001 F
b0 $
b0 >
1'
#506000
0@
b111111101100 D
b111111101011 E
b111010111100 ?
b100100 =
b0 +
b1000 )
0*
b1001 .
b1001 6
b1100010 /
b1100010 7
b11011100 (
b11011100 5
b110000 4
10
#510000
0'
#515000
0#
b0 "
b0 F
b1000 $
b1000 >
1'
#516000
1@
b111 A
b111110 D
b0 C
b111110 E
b1111101000 ?
b1100100 =
0,
b1100100 +
b0 )
1*
01
b1010 .
b1010 6
b100000 /
b100000 7
b1100100 (
b1100100 5
b110001 4
10
#520000
0'
#525000
1#
b1100100 "
b1100100 F
b0 $
b0 >
1'
#526000
b1000 A
b111111110010 D
b1 C
b111111110001 E
b111100011000 ?
b1110100 =
1,
b10001100 +
11
b10 .
b10 6
b1011000 /
b1011000 7
b10001100 (
b10001100 5
b110010 4
10
#530000
0'
#535000
b10001100 "
b10001100 F
1'
#536000
b111 A
b1010000 D
b0 C
b1010000 E
b10100001000 ?
b1011100 =
0,
b1011100 +
01
b1110 .
b1110 6
b11010 /
b11010 7
b1011100 (
b1011100 5
b110011 4
10
#540000
0'
#545000
b1011100 "
b1011100 F
1'
#546000
b1000 A
b111111011000 D
0B
b111111011000 E
b110110000101 ?
b1111111 =
b10000001 +
b101 .
b101 6
b11011 /
b11011 7
b10000001 (
b10000001 5
b110100 4
10
#550000
0'
#555000
b10000001 "
b10000001 F
1'
#556000
b0 A
b0 D
b0 E
b0 ?
b1000111 =
1,
b10111001 +
11
b0 .
b0 6
b1000011 /
b1000011 7
b10111001 (
b10111001 5
b110101 4
10
#560000
0'
#565000
b10111001 "
b10111001 F
1'
#566000
0@
b1000 A
b111111101001 D
1B
b111111101001 E
b111010011000 ?
b11110 =
0,
b0 +
b1000 )
0*
01
b1100 .
b1100 6
b1001111 /
b1001111 7
b11100010 (
b11100010 5
b110110 4
10
#570000
0'
#575000
0#
b0 "
b0 F
b1000 $
b1000 >
1'
#576000
b0 A
b0 D
0B
b0 E
b0 ?
b10101 =
b0 )
b0 .
b0 6
b11110 /
b11110 7
b11101011 (
b11101011 5
b110111 4
10
#580000
0'
#585000
b0 $
b0 >
1'
#586000
1@
b1000 A
b111111101000 D
b1 C
1B
b111111100111 E
b111001111111 ?
b100011 =
1,
b11011101 +
1*
11
b1011 .
b1011 6
b10101 /
b10101 7
b11011101 (
b11011101 5
b111000 4
10
#590000
0'
#595000
1#
b11011101 "
b11011101 F
1'
#596000
b0 A
b0 D
b0 C
0B
b0 E
b0 ?
b110110 =
0,
b11001010 +
01
b0 .
b0 6
b1111 /
b1111 7
b11001010 (
b11001010 5
b111001 4
10
#600000
0'
#605000
b11001010 "
b11001010 F
1'
#606000
b1000 A
b111111101000 D
1B
b111111101000 E
b111010001001 ?
b1111101 =
b10000011 +
b11 .
b11 6
b1011011 /
b1011011 7
b10000011 (
b10000011 5
b111010 4
10
#610000
0'
#615000
b10000011 "
b10000011 F
1'
#616000
b111111010000 D
0B
b111111010000 E
b110100000000 ?
b1100000 =
b10100000 +
b1000 .
b1000 6
b1011010 /
b1011010 7
b10100000 (
b10100000 5
b111011 4
10
#620000
0'
#625000
b10100000 "
b10100000 F
1'
#626000
b111 A
b100000 D
b1 C
1B
b11111 E
b111111100 ?
b1111111 =
1,
b1111111 +
11
b100 .
b100 6
b101010 /
b101010 7
b1111111 (
b1111111 5
b111100 4
10
#630000
0'
#635000
b1111111 "
b1111111 F
1'
#636000
b110100 D
b0 C
b110100 E
b1101001110 ?
b1011110 =
0,
b1011110 +
01
b1001 .
b1001 6
b1001101 /
b1001101 7
b1011110 (
b1011110 5
b111101 4
10
#640000
0'
#645000
b1011110 "
b1011110 F
1'
#646000
b11100 D
0B
b11100 E
b111000111 ?
b1000001 =
1,
b1000001 +
11
b111 .
b111 6
b101000 /
b101000 7
b1000001 (
b1000001 5
b111110 4
10
#650000
0'
#655000
b1000001 "
b1000001 F
1'
#656000
0@
b11011 D
1B
b11011 E
b110111100 ?
b1001010 =
0,
b0 +
b111 )
0*
01
b110 .
b110 6
b1100100 /
b1100100 7
b1001010 (
b1001010 5
b111111 4
10
#660000
0'
#665000
0#
b0 "
b0 F
b111 $
b111 >
1'
#666000
1@
b100110 D
b1 C
b100101 E
b1001011000 ?
b1001011 =
1,
b1001011 +
b0 )
1*
11
b1000 .
b1000 6
b1011 /
b1011 7
b1001011 (
b1001011 5
b1000000 4
10
#670000
0'
#675000
1#
b1001011 "
b1001011 F
b0 $
b0 >
1'
#676000
b1101010 D
b1101001 E
b11010011111 ?
b1110001 =
b1110001 +
b1111 .
b1111 6
b100000 /
b100000 7
b1110001 (
b1110001 5
b1000001 4
10
#680000
0'
#685000
b1110001 "
b1110001 F
1'
#686000
0@
b10 A
b10 D
b0 C
b10 E
b101000 ?
b100 =
0,
b0 +
b10 )
0*
01
b1010 .
b1010 6
b1100000 /
b1100000 7
b100 (
b100 5
b1000010 4
10
#690000
0'
#695000
0#
b0 "
b0 F
b10 $
b10 >
1'
#696000
1@
b1000 A
b111111110111 D
0B
b111111110111 E
b111101110100 ?
b1000110 =
b10111010 +
b0 )
1*
b10 .
b10 6
b101111 /
b101111 7
b10111010 (
b10111010 5
b1000011 4
10
#700000
0'
#705000
1#
b10111010 "
b10111010 F
b0 $
b0 >
1'
#706000
b111 A
b101101 D
b101101 E
b1011010110 ?
b1000010 =
1,
b1000010 +
11
b1011 .
b1011 6
b11 /
b11 7
b1000010 (
b1000010 5
b1000100 4
10
#710000
0'
#715000
b1000010 "
b1000010 F
1'
#716000
b1000 A
b111111100000 D
b111111100000 E
b111000000101 ?
b100111 =
b11011001 +
b1101 .
b1101 6
b11100 /
b11100 7
b11011001 (
b11011001 5
b1000101 4
10
#720000
0'
#725000
b11011001 "
b11011001 F
1'
#726000
0@
b0 A
b0 D
b0 E
b0 ?
b1 =
b0 +
0*
b0 .
b0 6
b1000 /
b1000 7
b11111111 (
b11111111 5
b1000110 4
10
#730000
0'
#735000
0#
b0 "
b0 F
1'
#736000
b111 A
b1010 D
1B
b1010 E
b10101110 ?
b111010 =
0,
b111 )
01
b11 .
b11 6
b1000110 /
b1000110 7
b111010 (
b111010 5
b1000111 4
10
#740000
0'
#745000
b111 $
b111 >
1'
#746000
1@
b0 A
b0 D
0B
b0 E
b0 ?
b1111001 =
1,
b1111001 +
b0 )
1*
11
b0 .
b0 6
b1101 /
b1101 7
b1111001 (
b1111001 5
b1001000 4
10
#750000
0'
#755000
1#
b1111001 "
b1111001 F
b0 $
b0 >
1'
#756000
b1000 A
b111111000100 D
1B
b111111000100 E
b110001001100 ?
b1001111 =
0,
b10110001 +
01
b1100 .
b1100 6
b101010 /
b101010 7
b10110001 (
b10110001 5
b1001001 4
10
#760000
0'
#765000
b10110001 "
b10110001 F
1'
#766000
0@
b111111010101 D
b111111010101 E
b110101011100 ?
b110100 =
b0 +
b1000 )
0*
b1101 .
b1101 6
b1011000 /
b1011000 7
b11001100 (
b11001100 5
b1001010 4
10
#770000
0'
#775000
0#
b0 "
b0 F
b1000 $
b1000 >
1'
#776000
1@
b111111011010 D
b111111011010 E
b110110101110 ?
b110110 =
b11001010 +
b0 )
1*
b1011 .
b1011 6
b110000 /
b110000 7
b11001010 (
b11001010 5
b1001011 4
10
#780000
0'
#785000
1#
b11001010 "
b11001010 F
b0 $
b0 >
1'
#786000
0@
b111111011011 D
0B
b111111011011 E
b110110110111 ?
b100111 =
1,
b0 +
b1000 )
0*
11
b1111 .
b1111 6
b111101 /
b111101 7
b11011001 (
b11011001 5
b1001100 4
10
#790000
0'
#795000
0#
b0 "
b0 F
b1000 $
b1000 >
1'
#796000
1@
b111111000111 D
1B
b111111000111 E
b110001111100 ?
b111100 =
0,
b11000100 +
b0 )
1*
01
b101101 /
b101101 7
b11000100 (
b11000100 5
b1001101 4
10
#800000
0'
#805000
1#
b11000100 "
b11000100 F
b0 $
b0 >
1'
#806000
b111 A
b1100101 D
b1 C
b1100100 E
b11001001010 ?
b1110011 =
1,
b1110011 +
11
b1110 .
b1110 6
b1001010 /
b1001010 7
b1110011 (
b1110011 5
b1001110 4
10
#810000
0'
#815000
b1110011 "
b1110011 F
1'
#816000
b1011 A
b111111111011 D
b0 C
0B
b111111111011 E
b111110110100 ?
b100110 =
0,
b11011010 +
01
b10 .
b10 6
b10000 /
b10000 7
b11011010 (
b11011010 5
b1001111 4
10
#820000
0'
#825000
b11011010 "
b11011010 F
1'
#826000
b1000 A
b111111001011 D
1B
b111111001011 E
b110010111011 ?
b1011101 =
b10100011 +
b1001 .
b1001 6
b100111 /
b100111 7
b10100011 (
b10100011 5
b1010000 4
10
#830000
0'
#835000
b10100011 "
b10100011 F
1'
#836000
b111110110111 D
b1 C
b111110110110 E
b101101101000 ?
b1100010 =
1,
b10011110 +
11
b1100 .
b1100 6
b1011010 /
b1011010 7
b10011110 (
b10011110 5
b1010001 4
10
#840000
0'
#845000
b10011110 "
b10011110 F
1'
#846000
0@
b111 A
b10001 D
b10000 E
b100001110 ?
b10010 =
b0 +
b111 )
0*
b1111 .
b1111 6
b1000100 /
b1000100 7
b10010 (
b10010 5
b1010010 4
10
#850000
0'
#855000
0#
b0 "
b0 F
b111 $
b111 >
1'
#856000
1@
b1000 A
b111111010100 D
b0 C
0B
b111111010100 E
b110101000010 ?
b1110101 =
b10001011 +
b0 )
1*
b110 .
b110 6
b1110 /
b1110 7
b10001011 (
b10001011 5
b1010011 4
10
#860000
0'
#865000
1#
b10001011 "
b10001011 F
b0 $
b0 >
1'
#866000
0@
b111111100011 D
b111111100011 E
b111000110000 ?
b111010 =
b0 +
b1000 )
0*
b1000 .
b1000 6
b1010011 /
b1010011 7
b11000110 (
b11000110 5
b1010100 4
10
#870000
0'
#875000
0#
b0 "
b0 F
b1000 $
b1000 >
1'
#876000
1@
b111110100011 D
b111110100011 E
b101000110100 ?
b1101010 =
b10010110 +
b0 )
1*
b1110 .
b1110 6
b1001100 /
b1001100 7
b10010110 (
b10010110 5
b1010101 4
10
#880000
0'
#885000
1#
b10010110 "
b10010110 F
b0 $
b0 >
1'
#886000
0@
b10 A
b10 D
b1 C
1B
b1 E
b11011 ?
b11 =
b0 +
b10 )
0*
b1001 .
b1001 6
b110 /
b110 7
b11 (
b11 5
b1010110 4
10
#890000
0'
#895000
0#
b0 "
b0 F
b10 $
b10 >
1'
#896000
b111 A
b11100 D
b0 C
0B
b11100 E
b111000111 ?
b1011011 =
b111 )
b101 .
b101 6
b1100000 /
b1100000 7
b1011011 (
b1011011 5
b1010111 4
10
#900000
0'
#905000
b111 $
b111 >
1'
#906000
b1100 A
b111111111100 D
b111111111100 E
b111111000001 ?
b10101 =
0,
b1100 )
01
b11 .
b11 6
b1000110 /
b1000110 7
b11101011 (
b11101011 5
b1011000 4
10
#910000
0'
#915000
b1100 $
b1100 >
1'
