rung4-gear-quantizer/rtl/gear_quantizer.sv
module gear_quantizer #(
    parameter int DATA_WIDTH = 8,
    parameter int INT4_WIDTH = 4
)(
    input logic signed [DATA_WIDTH-1:0] data_in,
    input logic  [INT4_WIDTH-1:0] scale,
    input logic valid_in,
    input logic [DATA_WIDTH-1:0] threshold,
    output logic signed [INT4_WIDTH-1:0] int4_out,
    output logic valid_out,
    output logic signed [DATA_WIDTH-1:0] sideband_out,
    output logic is_outlier,
    input logic clk,
    input logic rst_n,
    input logic round_mode
);

logic  [DATA_WIDTH-1:0] abs_data_in;
logic signed  [DATA_WIDTH + INT4_WIDTH - 1:0] mult_res;
logic signed  [INT4_WIDTH-1:0] post_clip_res;
logic outlier_comp_res;

localparam signed [INT4_WIDTH-1:0] INT4_MAX =  (1 << (INT4_WIDTH-1)) - 1;
localparam signed [INT4_WIDTH-1:0] INT4_MIN = -(1 << (INT4_WIDTH-1));

always_comb begin
    abs_data_in = (data_in[DATA_WIDTH-1]) ? -data_in : data_in;
    mult_res = data_in * $signed({1'b0, scale});
    post_clip_res = (mult_res > INT4_MAX) ? INT4_MAX : (mult_res < INT4_MIN) ? INT4_MIN : mult_res[INT4_WIDTH-1:0];
    outlier_comp_res = (abs_data_in > threshold);
end

always_ff @(posedge clk or negedge rst_n) begin
    if (!rst_n) begin
        int4_out <= '0;
        valid_out <= 1'b0;
        sideband_out <= '0;
        is_outlier <= 1'b0;
    end else begin
        valid_out <= valid_in;
        if (valid_in) begin
            int4_out <= outlier_comp_res ? '0 : post_clip_res;
            sideband_out <= outlier_comp_res ? data_in : '0;
            is_outlier <= outlier_comp_res;
        end
    end
end
endmodule

rung4-gear-quantizer/tb/tb_gear_quantizer.sv
`timescale 1ns/1ps

module tb_gear_quantizer;

    // DUT parameters
    localparam int DATA_WIDTH = 8;
    localparam int INT4_WIDTH = 4;

    // DUT signals
    logic                          clk, rst_n;
    logic                          valid_in, valid_out;
    logic signed [DATA_WIDTH-1:0]  data_in;
    logic        [DATA_WIDTH-1:0]  threshold;
    logic        [INT4_WIDTH-1:0]  scale;
    logic                          round_mode;
    logic signed [INT4_WIDTH-1:0]  int4_out;
    logic signed [DATA_WIDTH-1:0]  sideband_out;
    logic                          is_outlier;

    // DUT instantiation
    gear_quantizer #(
        .DATA_WIDTH(DATA_WIDTH),
        .INT4_WIDTH(INT4_WIDTH)
    ) dut (.*);

    // Clock
    initial clk = 0;
    always #5 clk = ~clk;  // 100 MHz

task automatic send(
    input logic signed [DATA_WIDTH-1:0] d_in,
    input logic        [DATA_WIDTH-1:0] thresh,
    input logic        [INT4_WIDTH-1:0] sc
);
    data_in   = d_in;
    threshold = thresh;
    scale     = sc;
    valid_in  = 1;
    @(posedge clk); #1;
    valid_in = 0;
endtask

task automatic check(
    input logic signed [INT4_WIDTH-1:0] exp_int4,
    input logic                         exp_outlier,
    input logic signed [DATA_WIDTH-1:0] exp_sideband,
    input string label
);
    if (valid_out !== 1'b1)
        $display("FAIL [%s]: valid_out not high", label);
    else if (is_outlier !== exp_outlier)
        $display("FAIL [%s]: is_outlier got %0b exp %0b", label, is_outlier, exp_outlier);
    else if (exp_outlier && sideband_out !== exp_sideband)
        $display("FAIL [%s]: sideband got %0d exp %0d", label, sideband_out, exp_sideband);
    else if (!exp_outlier && int4_out !== exp_int4)
        $display("FAIL [%s]: int4_out got %0d exp %0d", label, int4_out, exp_int4);
    else
        $display("PASS [%s]", label);
endtask

initial begin
    $dumpfile("sim/waves.vcd");
    $dumpvars(0, tb_gear_quantizer);
    clk = 0; rst_n = 0; valid_in = 0;
    round_mode = 0; scale = 0; threshold = 0;
    repeat(2) @(posedge clk);
    rst_n = 1;
    @(posedge clk); #1;

    send(8,   20, 2); check(7,  0,   0,  "Test 1: Normal quantization");
    send(30,  20, 2); check(0,  1,  30,  "Test 2: Positive outlier");
    send(-25, 20, 2); check(0,  1, -25,  "Test 3: Negative outlier");
    send(20,  20, 1); check(7,  0,   0,  "Test 4: Boundary (abs==threshold)");
    send(10,  20, 0); check(0,  0,   0,  "Test 5: Scale zero");
    send(-4,  20, 1); check(-4, 0,   0,  "Test 6: Negative normal");

    $display("\nAll tests done.");
    $finish;
end

endmodule

rung4-gear-quantizer/sim/waves.vcd
$date
	Tue Jun 30 16:27:48 2026
$end
$version
	Icarus Verilog
$end
$timescale
	1ps
$end
$scope module tb_gear_quantizer $end
$var wire 1 ! valid_out $end
$var wire 8 " sideband_out [7:0] $end
$var wire 1 # is_outlier $end
$var wire 4 $ int4_out [3:0] $end
$var parameter 32 % DATA_WIDTH $end
$var parameter 32 & INT4_WIDTH $end
$var reg 1 ' clk $end
$var reg 8 ( data_in [7:0] $end
$var reg 1 ) round_mode $end
$var reg 1 * rst_n $end
$var reg 4 + scale [3:0] $end
$var reg 8 , threshold [7:0] $end
$var reg 1 - valid_in $end
$scope module dut $end
$var wire 1 ' clk $end
$var wire 8 . data_in [7:0] $end
$var wire 1 ) round_mode $end
$var wire 1 * rst_n $end
$var wire 4 / scale [3:0] $end
$var wire 8 0 threshold [7:0] $end
$var wire 1 - valid_in $end
$var parameter 32 1 DATA_WIDTH $end
$var parameter 4 2 INT4_MAX $end
$var parameter 4 3 INT4_MIN $end
$var parameter 32 4 INT4_WIDTH $end
$var reg 8 5 abs_data_in [7:0] $end
$var reg 4 6 int4_out [3:0] $end
$var reg 1 # is_outlier $end
$var reg 12 7 mult_res [11:0] $end
$var reg 1 8 outlier_comp_res $end
$var reg 4 9 post_clip_res [3:0] $end
$var reg 8 : sideband_out [7:0] $end
$var reg 1 ! valid_out $end
$upscope $end
$scope task check $end
$upscope $end
$scope task send $end
$upscope $end
$upscope $end
$enddefinitions $end
$comment Show the parameter values. $end
$dumpall
b100 4
b1000 3
b111 2
b1000 1
b100 &
b1000 %
$end
#0
$dumpvars
b0 :
bx 9
x8
bx 7
b0 6
bx 5
b0 0
b0 /
bx .
0-
b0 ,
b0 +
0*
0)
bx (
0'
b0 $
0#
b0 "
0!
$end
#5000
1'
#10000
0'
#15000
1*
1'
#20000
0'
#25000
1'
#26000
08
b111 9
b10000 7
b1000 5
1-
b10 +
b10 /
b10100 ,
b10100 0
b1000 (
b1000 .
#30000
0'
#35000
b111 $
b111 6
1!
1'
#36000
18
b111100 7
b11110 5
b11110 (
b11110 .
1-
#40000
0'
#45000
1#
b11110 "
b11110 :
b0 $
b0 6
1'
#46000
b1000 9
b111111001110 7
b11001 5
b11100111 (
b11100111 .
1-
#50000
0'
#55000
b11100111 "
b11100111 :
1'
#56000
08
b111 9
b10100 7
b10100 5
b1 +
b1 /
b10100 (
b10100 .
1-
#60000
0'
#65000
0#
b0 "
b0 :
b111 $
b111 6
1'
#66000
b0 9
b0 7
b1010 5
b0 +
b0 /
b1010 (
b1010 .
1-
#70000
0'
#75000
b0 $
b0 6
1'
#76000
b1100 9
b111111111100 7
b100 5
b1 +
b1 /
b11111100 (
b11111100 .
1-
#80000
0'
#85000
b1100 $
b1100 6
1'
#86000
0-
