rung4-gear-quantizer/rtl/gear_quantizer.sv
module gear_quantizer #(
    parameter int DATA_WIDTH = 8,
    parameter int INT4_WIDTH = 4
)(
    input logic signed [DATA_WIDTH-1:0] data_in,
    input logic  [INT4_WIDTH-1:0] scale,
    input logic valid_in,
    input logic [DATA_WIDTH-1:0] threshold,
    output logic signed [INT4_WIDTH-1:0] int4_out,
    output logic valid_out,
    output logic signed [DATA_WIDTH-1:0] sideband_out,
    output logic is_outlier,
    input logic clk,
    input logic rst_n,
    input logic round_mode
);

logic  [DATA_WIDTH-1:0] abs_data_in;
logic signed  [DATA_WIDTH + INT4_WIDTH - 1:0] mult_res;
logic signed  [INT4_WIDTH-1:0] post_clip_res;
logic outlier_comp_res;

localparam signed [INT4_WIDTH-1:0] INT4_MAX =  (1 << (INT4_WIDTH-1)) - 1;
localparam signed [INT4_WIDTH-1:0] INT4_MIN = -(1 << (INT4_WIDTH-1));

always_comb begin
    abs_data_in = (data_in[DATA_WIDTH-1]) ? -data_in : data_in;
    mult_res = data_in * $signed({1'b0, scale});
    post_clip_res = (mult_res > INT4_MAX) ? INT4_MAX : (mult_res < INT4_MIN) ? INT4_MIN : mult_res[INT4_WIDTH-1:0];
    outlier_comp_res = (abs_data_in > threshold);
end

always_ff @(posedge clk or negedge rst_n) begin
    if (!rst_n) begin
        int4_out <= '0;
        valid_out <= 1'b0;
        sideband_out <= '0;
        is_outlier <= 1'b0;
    end else begin
        valid_out <= valid_in;
        if (valid_in) begin
            int4_out <= outlier_comp_res ? '0 : post_clip_res;
            sideband_out <= outlier_comp_res ? data_in : '0;
            is_outlier <= outlier_comp_res;
        end
    end
end
endmodule

rung4-gear-quantizer/tb/tb_cosim.sv
`timescale 1ns/1ps
module tb_cosim;

    localparam int DATA_WIDTH = 8;
    localparam int INT4_WIDTH = 4;

    logic                         clk, rst_n, valid_in, valid_out;
    logic signed [DATA_WIDTH-1:0] data_in;
    logic        [DATA_WIDTH-1:0] threshold;
    logic        [INT4_WIDTH-1:0] scale;
    logic                         round_mode;
    logic signed [INT4_WIDTH-1:0] int4_out;
    logic signed [DATA_WIDTH-1:0] sideband_out;
    logic                         is_outlier;

    gear_quantizer #(.DATA_WIDTH(DATA_WIDTH), .INT4_WIDTH(INT4_WIDTH)) dut (.*);

    initial clk = 0;
    always #5 clk = ~clk;

    // expected values read from file
    logic signed [DATA_WIDTH-1:0] exp_sideband;
    logic signed [INT4_WIDTH-1:0] exp_int4;
    logic                         exp_outlier;

    int fd, passes, fails;

    initial begin
        $dumpfile("sim/waves_cosim.vcd");
        $dumpvars(0, tb_cosim);
        clk = 0; rst_n = 0; valid_in = 0; round_mode = 0;
        repeat(2) @(posedge clk);
        rst_n = 1;
        @(posedge clk); #1;

        passes = 0; fails = 0;
        fd = $fopen("sim/vectors.txt", "r");

        while (!$feof(fd)) begin
            if ($fscanf(fd, "%d %d %d %d %d %d\n",
                        data_in, threshold, scale,
                        exp_outlier, exp_int4, exp_sideband) == 6) begin
                // drive and check — what goes here?
                valid_in = 1;
                @(posedge clk); #1;
                valid_in = 0;
                if (valid_out !== 1'b1) begin
                    $display("FAIL: valid_out not high");
                    fails++;
                end else if (is_outlier !== exp_outlier) begin
                    $display("FAIL: is_outlier got %0b exp %0b", is_outlier, exp_outlier);
                    fails++;
                end else if (exp_outlier && sideband_out !== exp_sideband) begin
                    $display("FAIL: sideband got %0d exp %0d", sideband_out, exp_sideband);
                    fails++;
                end else if (!exp_outlier && int4_out !== exp_int4) begin
                    $display("FAIL: int4_out got %0d exp %0d", int4_out, exp_int4);
                    fails++;
                end else begin
                    $display("PASS");
                    passes++;
                end           // closes else begin
            end               // closes if ($fscanf) begin
        end                   // closes while begin

        $fclose(fd);
        $display("\nCo-sim done: %0d/%0d passed", passes, passes+fails);
        $finish;
    end

endmodule

rung4-gear-quantizer/sim/waves_cosim.vcd
$date
	Tue Jun 30 17:21:21 2026
$end
$version
	Icarus Verilog
$end
$timescale
	1ps
$end
$scope module tb_cosim $end
$var wire 1 ! valid_out $end
$var wire 8 " sideband_out [7:0] $end
$var wire 1 # is_outlier $end
$var wire 4 $ int4_out [3:0] $end
$var parameter 32 % DATA_WIDTH $end
$var parameter 32 & INT4_WIDTH $end
$var reg 1 ' clk $end
$var reg 8 ( data_in [7:0] $end
$var reg 4 ) exp_int4 [3:0] $end
$var reg 1 * exp_outlier $end
$var reg 8 + exp_sideband [7:0] $end
$var reg 1 , round_mode $end
$var reg 1 - rst_n $end
$var reg 4 . scale [3:0] $end
$var reg 8 / threshold [7:0] $end
$var reg 1 0 valid_in $end
$var integer 32 1 fails [31:0] $end
$var integer 32 2 fd [31:0] $end
$var integer 32 3 passes [31:0] $end
$scope module dut $end
$var wire 1 ' clk $end
$var wire 8 4 data_in [7:0] $end
$var wire 1 , round_mode $end
$var wire 1 - rst_n $end
$var wire 4 5 scale [3:0] $end
$var wire 8 6 threshold [7:0] $end
$var wire 1 0 valid_in $end
$var parameter 32 7 DATA_WIDTH $end
$var parameter 4 8 INT4_MAX $end
$var parameter 4 9 INT4_MIN $end
$var parameter 32 : INT4_WIDTH $end
$var reg 8 ; abs_data_in [7:0] $end
$var reg 4 < int4_out [3:0] $end
$var reg 1 # is_outlier $end
$var reg 12 = mult_res [11:0] $end
$var reg 1 > outlier_comp_res $end
$var reg 4 ? post_clip_res [3:0] $end
$var reg 8 @ sideband_out [7:0] $end
$var reg 1 ! valid_out $end
$upscope $end
$upscope $end
$enddefinitions $end
$comment Show the parameter values. $end
$dumpall
b100 :
b1000 9
b111 8
b1000 7
b100 &
b1000 %
$end
#0
$dumpvars
b0 @
bx ?
x>
bx =
b0 <
bx ;
bx 6
bx 5
bx 4
b0 3
b0 2
b0 1
00
bx /
bx .
0-
0,
bx +
x*
bx )
bx (
0'
b0 $
0#
b0 "
0!
$end
#5000
1'
#10000
0'
#15000
1-
1'
#20000
0'
#25000
1'
#26000
1>
b1000 ?
b111100101110 =
b11110 ;
10
b11100010 +
b0 )
1*
b111 .
b111 5
b101 /
b101 6
b11100010 (
b11100010 4
b10000000000000000000000000000011 2
#30000
0'
#35000
1#
b11100010 "
b11100010 @
1!
1'
#36000
b111 ?
b10001110100 =
b1001100 ;
b1001100 +
b1111 .
b1111 5
b111100 /
b111100 6
b1001100 (
b1001100 4
b1 3
10
#40000
0'
#45000
b1001100 "
b1001100 @
1'
#46000
0>
b1000 ?
b111000100000 =
b110000 ;
b0 +
b1000 )
0*
b1010 .
b1010 5
b1100011 /
b1100011 6
b11010000 (
b11010000 4
b10 3
10
#50000
0'
#55000
0#
b0 "
b0 @
b1000 $
b1000 <
1'
#56000
b101 ?
b101 =
b101 ;
b101 )
b1 .
b1 5
b110111 /
b110111 6
b101 (
b101 4
b11 3
10
#60000
0'
#65000
b101 $
b101 <
1'
#66000
1>
b111 ?
b10111001100 =
b1101010 ;
b1101010 +
b0 )
1*
b1110 .
b1110 5
b1101 /
b1101 6
b1101010 (
b1101010 4
b100 3
10
#70000
0'
#75000
1#
b1101010 "
b1101010 @
b0 $
b0 <
1'
#76000
b1000 ?
b110001001000 =
b1110111 ;
b10001001 +
b1000 .
b1000 5
b11 /
b11 6
b10001001 (
b10001001 4
b101 3
10
#80000
0'
#85000
b10001001 "
b10001001 @
1'
#86000
0>
b0 ?
b0 =
b101111 ;
b0 +
0*
b0 .
b0 5
b111111 /
b111111 6
b101111 (
b101111 4
b110 3
10
#90000
0'
#95000
0#
b0 "
b0 @
1'
#96000
1>
b111 ?
b10000010100 =
b1110100 ;
b1110100 +
1*
b1001 .
b1001 5
b101 /
b101 6
b1110100 (
b1110100 4
b111 3
10
#100000
0'
#105000
1#
b1110100 "
b1110100 @
1'
#106000
b10110111110 =
b1100010 ;
b1100010 +
b1111 .
b1111 5
b1001110 /
b1001110 6
b1100010 (
b1100010 4
b1000 3
10
#110000
0'
#115000
b1100010 "
b1100010 @
1'
#116000
0>
b1000 ?
b111011010111 =
b11011 ;
b0 +
b1000 )
0*
b1011 .
b1011 5
b111000 /
b111000 6
b11100101 (
b11100101 4
b1001 3
10
#120000
0'
#125000
0#
b0 "
b0 @
b1000 $
b1000 <
1'
#126000
1>
b111111000100 =
b1010 ;
b11110110 +
b0 )
1*
b110 .
b110 5
b100 /
b100 6
b11110110 (
b11110110 4
b1010 3
10
#130000
0'
#135000
1#
b11110110 "
b11110110 @
b0 $
b0 <
1'
#136000
b111111010110 =
b11 ;
b11111101 +
b1110 .
b1110 5
b0 /
b0 6
b11111101 (
b11111101 4
b1011 3
10
#140000
0'
#145000
b11111101 "
b11111101 @
1'
#146000
b111 ?
b10101001001 =
b1111011 ;
b1111011 +
b1011 .
b1011 5
b110001 /
b110001 6
b1111011 (
b1111011 4
b1100 3
10
#150000
0'
#155000
b1111011 "
b1111011 @
1'
#156000
0>
b1000 ?
b111000100110 =
b1001111 ;
b0 +
b1000 )
0*
b110 .
b110 5
b1001111 /
b1001111 6
b10110001 (
b10110001 4
b1101 3
10
#160000
0'
#165000
0#
b0 "
b0 @
b1000 $
b1000 <
1'
#166000
b111101110100 =
b11100 ;
b101 .
b101 5
b100001 /
b100001 6
b11100100 (
b11100100 4
b1110 3
10
#170000
0'
#175000
1'
#176000
b111 ?
b101000010 =
b101110 ;
b111 )
b111 .
b111 5
b1011110 /
b1011110 6
b101110 (
b101110 4
b1111 3
10
#180000
0'
#185000
b111 $
b111 <
1'
#186000
1>
b110011110 =
b101110 +
b0 )
1*
b1001 .
b1001 5
b11000 /
b11000 6
b10000 3
10
#190000
0'
#195000
1#
b101110 "
b101110 @
b0 $
b0 <
1'
#196000
0>
b1000 ?
b111111010000 =
b1100 ;
b0 +
b1000 )
0*
b100 .
b100 5
b10000 /
b10000 6
b11110100 (
b11110100 4
b10001 3
10
#200000
0'
#205000
0#
b0 "
b0 @
b1000 $
b1000 <
1'
#206000
b111 ?
b1000000000 =
b1000000 ;
b111 )
b1000 .
b1000 5
b1011000 /
b1011000 6
b1000000 (
b1000000 4
b10010 3
10
#210000
0'
#215000
b111 $
b111 <
1'
#216000
1>
b100101111 =
b1100101 ;
b1100101 +
b0 )
1*
b11 .
b11 5
b11001 /
b11001 6
b1100101 (
b1100101 4
b10011 3
10
#220000
0'
#225000
1#
b1100101 "
b1100101 @
b0 $
b0 <
1'
#226000
0>
b100101100 =
b110010 ;
b0 +
b111 )
0*
b110 .
b110 5
b111111 /
b111111 6
b110010 (
b110010 4
b10100 3
10
#230000
0'
#235000
0#
b0 "
b0 @
b111 $
b111 <
1'
#236000
1>
b10100010 =
b10010 ;
b10010 +
b0 )
1*
b1001 .
b1001 5
b0 /
b0 6
b10010 (
b10010 4
b10101 3
10
#240000
0'
#245000
1#
b10010 "
b10010 @
b0 $
b0 <
1'
#246000
b1000 ?
b111110011011 =
b1100101 ;
b10011011 +
b1 .
b1 5
b100100 /
b100100 6
b10011011 (
b10011011 4
b10110 3
10
#250000
0'
#255000
b10011011 "
b10011011 @
1'
#256000
b110101101100 =
b111100 ;
b11000100 +
b1011 .
b1011 5
b100101 /
b100101 6
b11000100 (
b11000100 4
b10111 3
10
#260000
0'
#265000
b11000100 "
b11000100 @
1'
#266000
0>
b111000100000 =
b101000 ;
b0 +
b1000 )
0*
b1100 .
b1100 5
b1000010 /
b1000010 6
b11011000 (
b11011000 4
b11000 3
10
#270000
0'
#275000
0#
b0 "
b0 @
b1000 $
b1000 <
1'
#276000
1>
b111111000000 =
b1000000 ;
b11000000 +
b0 )
1*
b1 .
b1 5
b10 /
b10 6
b11000000 (
b11000000 4
b11001 3
10
#280000
0'
#285000
1#
b11000000 "
b11000000 @
b0 $
b0 <
1'
#286000
b111 ?
b1000110000 =
b1110000 ;
b1110000 +
b101 .
b101 5
b100110 /
b100110 6
b1110000 (
b1110000 4
b11010 3
10
#290000
0'
#295000
b1110000 "
b1110000 @
1'
#296000
b1101111000 =
b1101111 ;
b1101111 +
b1000 .
b1000 5
b1010001 /
b1010001 6
b1101111 (
b1101111 4
b11011 3
10
#300000
0'
#305000
b1101111 "
b1101111 @
1'
#306000
b1000 ?
b111011111110 =
b1010110 ;
b10101010 +
b11 .
b11 5
b101110 /
b101110 6
b10101010 (
b10101010 4
b11100 3
10
#310000
0'
#315000
b10101010 "
b10101010 @
1'
#316000
b111101111000 =
b10001 ;
b11101111 +
b1000 .
b1000 5
b1101 /
b1101 6
b11101111 (
b11101111 4
b11101 3
10
#320000
0'
#325000
b11101111 "
b11101111 @
1'
#326000
b111 ?
b100100000 =
b100100 ;
b100100 +
b10001 /
b10001 6
b100100 (
b100100 4
b11110 3
10
#330000
0'
#335000
b100100 "
b100100 @
1'
#336000
0>
b1000 ?
b111111000100 =
b111100 ;
b0 +
b1000 )
0*
b1 .
b1 5
b1000111 /
b1000111 6
b11000100 (
b11000100 4
b11111 3
10
#340000
0'
#345000
0#
b0 "
b0 @
b1000 $
b1000 <
1'
#346000
b111111101000 =
b1000 ;
b11 .
b11 5
b110100 /
b110100 6
b11111000 (
b11111000 4
b100000 3
10
#350000
0'
#355000
1'
#356000
1>
b111 ?
b10110110 =
b1110 ;
b1110 +
b0 )
1*
b1101 .
b1101 5
b1100 /
b1100 6
b1110 (
b1110 4
b100001 3
10
#360000
0'
#365000
1#
b1110 "
b1110 @
b0 $
b0 <
1'
#366000
b110100111 =
b101111 ;
b101111 +
b1001 .
b1001 5
b11010 /
b11010 6
b101111 (
b101111 4
b100010 3
10
#370000
0'
#375000
b101111 "
b101111 @
1'
#376000
0>
b1001000 =
b1000 ;
b0 +
b111 )
0*
b111000 /
b111000 6
b1000 (
b1000 4
b100011 3
10
#380000
0'
#385000
0#
b0 "
b0 @
b111 $
b111 <
1'
#386000
b11001000 =
b10100 ;
b1010 .
b1010 5
b1100011 /
b1100011 6
b10100 (
b10100 4
b100100 3
10
#390000
0'
#395000
1'
#396000
1>
b1011100100 =
b1001010 ;
b1001010 +
b0 )
1*
b11011 /
b11011 6
b1001010 (
b1001010 4
b100101 3
10
#400000
0'
#405000
1#
b1001010 "
b1001010 @
b0 $
b0 <
1'
#406000
b1000111111 =
b1110011 ;
b1110011 +
b101 .
b101 5
b110010 /
b110010 6
b1110011 (
b1110011 4
b100110 3
10
#410000
0'
#415000
b1110011 "
b1110011 @
1'
#416000
b1000 ?
b111110111100 =
b1000100 ;
b10111100 +
b1 .
b1 5
b10000 /
b10000 6
b10111100 (
b10111100 4
b100111 3
10
#420000
0'
#425000
b10111100 "
b10111100 @
1'
#426000
0>
b111 ?
b1001110 =
b110 ;
b0 +
b111 )
0*
b1101 .
b1101 5
b10110 /
b10110 6
b110 (
b110 4
b101000 3
10
#430000
0'
#435000
0#
b0 "
b0 @
b111 $
b111 <
1'
#436000
1>
b101001010 =
b100001 ;
b100001 +
b0 )
1*
b1010 .
b1010 5
b11000 /
b11000 6
b100001 (
b100001 4
b101001 3
10
#440000
0'
#445000
1#
b100001 "
b100001 @
b0 $
b0 <
1'
#446000
0>
b1000 ?
b111110111011 =
b10111 ;
b0 +
b1000 )
0*
b11 .
b11 5
b1100000 /
b1100000 6
b11101001 (
b11101001 4
b101010 3
10
#450000
0'
#455000
0#
b0 "
b0 @
b1000 $
b1000 <
1'
#456000
b110110000011 =
b110001 ;
b1101 .
b1101 5
b110110 /
b110110 6
b11001111 (
b11001111 4
b101011 3
10
#460000
0'
#465000
1'
#466000
b111 ?
b1000101001 =
b1001111 ;
b111 )
b111 .
b111 5
b1001111 /
b1001111 6
b1001111 (
b1001111 4
b101100 3
10
#470000
0'
#475000
b111 $
b111 <
1'
#476000
1>
b1000 ?
b110101001011 =
b1001101 ;
b10110011 +
b0 )
1*
b1001 .
b1001 5
b111000 /
b111000 6
b10110011 (
b10110011 4
b101101 3
10
#480000
0'
#485000
1#
b10110011 "
b10110011 @
b0 $
b0 <
1'
#486000
0>
b111 ?
b100001100 =
b1000011 ;
b0 +
b111 )
0*
b100 .
b100 5
b1010101 /
b1010101 6
b1000011 (
b1000011 4
b101110 3
10
#490000
0'
#495000
0#
b0 "
b0 @
b111 $
b111 <
1'
#496000
1>
b111010110 =
b1011110 ;
b1011110 +
b0 )
1*
b101 .
b101 5
b100100 /
b100100 6
b1011110 (
b1011110 4
b101111 3
10
#500000
0'
#505000
1#
b1011110 "
b1011110 @
b0 $
b0 <
1'
#506000
0>
b1111111100 =
b1010101 ;
b0 +
b111 )
0*
b1100 .
b1100 5
b1011100 /
b1011100 6
b1010101 (
b1010101 4
b110000 3
10
#510000
0'
#515000
0#
b0 "
b0 @
b111 $
b111 <
1'
#516000
1>
b1000 ?
b111011100011 =
b1011111 ;
b10100001 +
b0 )
1*
b11 .
b11 5
b1001 /
b1001 6
b10100001 (
b10100001 4
b110001 3
10
#520000
0'
#525000
1#
b10100001 "
b10100001 @
b0 $
b0 <
1'
#526000
0>
b111 ?
b1011010 =
b10010 ;
b0 +
b111 )
0*
b101 .
b101 5
b1010100 /
b1010100 6
b10010 (
b10010 4
b110010 3
10
#530000
0'
#535000
0#
b0 "
b0 @
b111 $
b111 <
1'
#536000
b1000 ?
b111101110000 =
b1100 ;
b1000 )
b1100 .
b1100 5
b111110 /
b111110 6
b11110100 (
b11110100 4
b110011 3
10
#540000
0'
#545000
b1000 $
b1000 <
1'
#546000
b111 ?
b111111110 =
b110011 ;
b111 )
b1010 .
b1010 5
b1001010 /
b1001010 6
b110011 (
b110011 4
b110100 3
10
#550000
0'
#555000
b111 $
b111 <
1'
#556000
1>
b1100100 =
b1100100 ;
b1100100 +
b0 )
1*
b1 .
b1 5
b1011101 /
b1011101 6
b1100100 (
b1100100 4
b110101 3
10
#560000
0'
#565000
1#
b1100100 "
b1100100 @
b0 $
b0 <
1'
#566000
b1000 ?
b110110100101 =
b1000011 ;
b10111101 +
b1001 .
b1001 5
b1001 /
b1001 6
b10111101 (
b10111101 4
b110110 3
10
#570000
0'
#575000
b10111101 "
b10111101 @
1'
#576000
b100111011001 =
b1101001 ;
b10010111 +
b1111 .
b1111 5
b10111 /
b10111 6
b10010111 (
b10010111 4
b110111 3
10
#580000
0'
#585000
b10010111 "
b10010111 @
1'
#586000
0>
b111 ?
b101000100 =
b11011 ;
b0 +
b111 )
0*
b1100 .
b1100 5
b1001111 /
b1001111 6
b11011 (
b11011 4
b111000 3
10
#590000
0'
#595000
0#
b0 "
b0 @
b111 $
b111 <
1'
#596000
1>
b1100000010 =
b1000110 ;
b1000110 +
b0 )
1*
b1011 .
b1011 5
b111111 /
b111111 6
b1000110 (
b1000110 4
b111001 3
10
#600000
0'
#605000
1#
b1000110 "
b1000110 @
b0 $
b0 <
1'
#606000
0>
b1100000000 =
b1100000 ;
b0 +
b111 )
0*
b1000 .
b1000 5
b1100011 /
b1100011 6
b1100000 (
b1100000 4
b111010 3
10
#610000
0'
#615000
0#
b0 "
b0 @
b111 $
b111 <
1'
#616000
1>
b1000 ?
b111011001000 =
b11010 ;
b11100110 +
b0 )
1*
b1100 .
b1100 5
b10011 /
b10011 6
b11100110 (
b11100110 4
b111011 3
10
#620000
0'
#625000
1#
b11100110 "
b11100110 @
b0 $
b0 <
1'
#626000
0>
b111000111000 =
b1001100 ;
b0 +
b1000 )
0*
b110 .
b110 5
b1010001 /
b1010001 6
b10110100 (
b10110100 4
b111100 3
10
#630000
0'
#635000
0#
b0 "
b0 @
b1000 $
b1000 <
1'
#636000
b0 ?
b0 =
b100011 ;
b0 )
b0 .
b0 5
b1011101 /
b1011101 6
b100011 (
b100011 4
b111101 3
10
#640000
0'
#645000
b0 $
b0 <
1'
#646000
b1000 ?
b111101110000 =
b1001000 ;
b1000 )
b10 .
b10 5
b1001010 /
b1001010 6
b10111000 (
b10111000 4
b111110 3
10
#650000
0'
#655000
b1000 $
b1000 <
1'
#656000
1>
b101100001000 =
b1101010 ;
b10010110 +
b0 )
1*
b1100 .
b1100 5
b1000110 /
b1000110 6
b10010110 (
b10010110 4
b111111 3
10
#660000
0'
#665000
1#
b10010110 "
b10010110 @
b0 $
b0 <
1'
#666000
0>
b111 ?
b1010100011 =
b1001011 ;
b0 +
b111 )
0*
b1001 .
b1001 5
b1100010 /
b1100010 6
b1001011 (
b1001011 4
b1000000 3
10
#670000
0'
#675000
0#
b0 "
b0 @
b111 $
b111 <
1'
#676000
1>
b101010110 =
b1110010 ;
b1110010 +
b0 )
1*
b11 .
b11 5
b1000111 /
b1000111 6
b1110010 (
b1110010 4
b1000001 3
10
#680000
0'
#685000
1#
b1110010 "
b1110010 @
b0 $
b0 <
1'
#686000
b1111011100 =
b1001100 ;
b1001100 +
b1101 .
b1101 5
b1000010 /
b1000010 6
b1001100 (
b1001100 4
b1000010 3
10
#690000
0'
#695000
b1001100 "
b1001100 @
1'
#696000
0>
b1000 ?
b111110100000 =
b100000 ;
b0 +
b1000 )
0*
b11 .
b11 5
b1001110 /
b1001110 6
b11100000 (
b11100000 4
b1000011 3
10
#700000
0'
#705000
0#
b0 "
b0 @
b1000 $
b1000 <
1'
#706000
b111111001000 =
b111 ;
b1000 .
b1000 5
b11100 /
b11100 6
b11111001 (
b11111001 4
b1000100 3
10
#710000
0'
#715000
1'
#716000
1>
b111 ?
b10110010100 =
b1100110 ;
b1100110 +
b0 )
1*
b1110 .
b1110 5
b100100 /
b100100 6
b1100110 (
b1100110 4
b1000101 3
10
#720000
0'
#725000
1#
b1100110 "
b1100110 @
b0 $
b0 <
1'
#726000
0>
b0 ?
b0 =
b11000 ;
b0 +
0*
b0 .
b0 5
b101001 /
b101001 6
b11101000 (
b11101000 4
b1000110 3
10
#730000
0'
#735000
0#
b0 "
b0 @
1'
#736000
1>
b1000 ?
b111010010011 =
b1001001 ;
b10110111 +
1*
b101 .
b101 5
b101010 /
b101010 6
b10110111 (
b10110111 4
b1000111 3
10
#740000
0'
#745000
1#
b10110111 "
b10110111 @
1'
#746000
b111 ?
b111010 =
b111010 ;
b111010 +
b1 .
b1 5
b110001 /
b110001 6
b111010 (
b111010 4
b1001000 3
10
#750000
0'
#755000
b111010 "
b111010 @
1'
#756000
b1000110000 =
b111000 ;
b111000 +
b1010 .
b1010 5
b10001 /
b10001 6
b111000 (
b111000 4
b1001001 3
10
#760000
0'
#765000
b111000 "
b111000 @
1'
#766000
0>
b1000 ?
b110111000100 =
b101100 ;
b0 +
b1000 )
0*
b1101 .
b1101 5
b1011100 /
b1011100 6
b11010100 (
b11010100 4
b1001010 3
10
#770000
0'
#775000
0#
b0 "
b0 @
b1000 $
b1000 <
1'
#776000
1>
b111 ?
b1101001000 =
b1101001 ;
b1101001 +
b0 )
1*
b1000 .
b1000 5
b1 /
b1 6
b1101001 (
b1101001 4
b1001011 3
10
#780000
0'
#785000
1#
b1101001 "
b1101001 @
b0 $
b0 <
1'
#786000
b10010001000 =
b1110100 ;
b1110100 +
b1010 .
b1010 5
b100011 /
b100011 6
b1110100 (
b1110100 4
b1001100 3
10
#790000
0'
#795000
b1110100 "
b1110100 @
1'
#796000
b1000 ?
b111011001000 =
b1101000 ;
b10011000 +
b11 .
b11 5
b1011001 /
b1011001 6
b10011000 (
b10011000 4
b1001101 3
10
#800000
0'
#805000
b10011000 "
b10011000 @
1'
#806000
b0 ?
b0 =
b1111011 ;
b1111011 +
b0 .
b0 5
b101001 /
b101001 6
b1111011 (
b1111011 4
b1001110 3
10
#810000
0'
#815000
b1111011 "
b1111011 @
1'
#816000
0>
b111 ?
b11110 =
b1010 ;
b0 +
b111 )
0*
b11 .
b11 5
b110001 /
b110001 6
b1010 (
b1010 4
b1001111 3
10
#820000
0'
#825000
0#
b0 "
b0 @
b111 $
b111 <
1'
#826000
1>
b100100110 =
b1100010 ;
b1100010 +
b0 )
1*
b1010000 /
b1010000 6
b1100010 (
b1100010 4
b1010000 3
10
#830000
0'
#835000
1#
b1100010 "
b1100010 @
b0 $
b0 <
1'
#836000
b11001111 =
b10111 ;
b10111 +
b1001 .
b1001 5
b100 /
b100 6
b10111 (
b10111 4
b1010001 3
10
#840000
0'
#845000
b10111 "
b10111 @
1'
#846000
b101000010 =
b101110 ;
b101110 +
b111 .
b111 5
b0 /
b0 6
b101110 (
b101110 4
b1010010 3
10
#850000
0'
#855000
b101110 "
b101110 @
1'
#856000
b1000 ?
b111000001000 =
b111111 ;
b11000001 +
b1000 .
b1000 5
b110001 /
b110001 6
b11000001 (
b11000001 4
b1010011 3
10
#860000
0'
#865000
b11000001 "
b11000001 @
1'
#866000
b111 ?
b1010000 =
b1000 ;
b1000 +
b1010 .
b1010 5
b10 /
b10 6
b1000 (
b1000 4
b1010100 3
10
#870000
0'
#875000
b1000 "
b1000 @
1'
#876000
b1000 ?
b110000111000 =
b1111001 ;
b10000111 +
b1000 .
b1000 5
b110000 /
b110000 6
b10000111 (
b10000111 4
b1010101 3
10
#880000
0'
#885000
b10000111 "
b10000111 @
1'
#886000
b111 ?
b1001001001 =
b101101 ;
b101101 +
b1101 .
b1101 5
b1 /
b1 6
b101101 (
b101101 4
b1010110 3
10
#890000
0'
#895000
b101101 "
b101101 @
1'
#896000
0>
b1010001001 =
b111011 ;
b0 +
b111 )
0*
b1011 .
b1011 5
b1000001 /
b1000001 6
b111011 (
b111011 4
b1010111 3
10
#900000
0'
#905000
0#
b0 "
b0 @
b111 $
b111 <
1'
#906000
1>
b1000 ?
b101111100011 =
b1110101 ;
b10001011 +
b0 )
1*
b1001 .
b1001 5
b1001111 /
b1001111 6
b10001011 (
b10001011 4
b1011000 3
10
#910000
0'
#915000
1#
b10001011 "
b10001011 @
b0 $
b0 <
1'
#916000
b110100111010 =
b1000111 ;
b10111001 +
b1010 .
b1010 5
b1110 /
b1110 6
b10111001 (
b10111001 4
b1011001 3
10
#920000
0'
#925000
b10111001 "
b10111001 @
1'
#926000
b0 ?
b0 =
b1100000 ;
b1100000 +
b0 .
b0 5
b101000 /
b101000 6
b1100000 (
b1100000 4
b1011010 3
10
#930000
0'
#935000
b1100000 "
b1100000 @
1'
#936000
0>
b111 ?
b111000 =
b100 ;
b0 +
b111 )
0*
b1110 .
b1110 5
b1011011 /
b1011011 6
b100 (
b100 4
b1011011 3
10
#940000
0'
#945000
0#
b0 "
b0 @
b111 $
b111 <
1'
#946000
1>
b1000 ?
b100011011010 =
b1111010 ;
b10000110 +
b0 )
1*
b1111 .
b1111 5
b11100 /
b11100 6
b10000110 (
b10000110 4
b1011100 3
10
#950000
0'
#955000
1#
b10000110 "
b10000110 @
b0 $
b0 <
1'
#956000
0>
b111 ?
b111111110 =
b100010 ;
b0 +
b111 )
0*
b1010101 /
b1010101 6
b100010 (
b100010 4
b1011101 3
10
#960000
0'
#965000
0#
b0 "
b0 @
b111 $
b111 <
1'
#966000
1>
b10000110110 =
b1001101 ;
b1001101 +
b0 )
1*
b1110 .
b1110 5
b11101 /
b11101 6
b1001101 (
b1001101 4
b1011110 3
10
#970000
0'
#975000
1#
b1001101 "
b1001101 @
b0 $
b0 <
1'
#976000
0>
b10100010 =
b11011 ;
b0 +
b111 )
0*
b110 .
b110 5
b110100 /
b110100 6
b11011 (
b11011 4
b1011111 3
10
#980000
0'
#985000
0#
b0 "
b0 @
b111 $
b111 <
1'
#986000
b1001100 =
b10011 ;
b100 .
b100 5
b1100011 /
b1100011 6
b10011 (
b10011 4
b1100000 3
10
#990000
0'
#995000
1'
#996000
b1000 ?
b111011101001 =
b1011101 ;
b1000 )
b11 .
b11 5
b1011110 /
b1011110 6
b10100011 (
b10100011 4
b1100001 3
10
#1000000
0'
#1005000
b1000 $
b1000 <
1'
#1006000
1>
b111 ?
b10011011 =
b11111 ;
b11111 +
b0 )
1*
b101 .
b101 5
b10111 /
b10111 6
b11111 (
b11111 4
b1100010 3
10
#1010000
0'
#1015000
1#
b11111 "
b11111 @
b0 $
b0 <
1'
#1016000
0>
b1000011 =
b1000011 ;
b0 +
b111 )
0*
b1 .
b1 5
b1011001 /
b1011001 6
b1000011 (
b1000011 4
b1100011 3
10
#1020000
0'
#1025000
0#
b0 "
b0 @
b111 $
b111 <
1'
#1026000
1>
b1000 ?
b111100100000 =
b1110000 ;
b10010000 +
b0 )
1*
b10 .
b10 5
b111001 /
b111001 6
b10010000 (
b10010000 4
b1100100 3
10
#1030000
0'
#1035000
1#
b10010000 "
b10010000 @
b0 $
b0 <
1'
#1036000
0>
b111010011000 =
b101000 ;
b0 +
b1000 )
0*
b1001 .
b1001 5
b1011110 /
b1011110 6
b11011000 (
b11011000 4
b1100101 3
10
#1040000
0'
#1045000
0#
b0 "
b0 @
b1000 $
b1000 <
1'
#1046000
1>
b111 ?
b1111000011 =
b1101011 ;
b1101011 +
b0 )
1*
b10001 /
b10001 6
b1101011 (
b1101011 4
b1100110 3
10
#1050000
0'
#1055000
1#
b1101011 "
b1101011 @
b0 $
b0 <
1'
#1056000
0>
b1000 ?
b111100111000 =
b11001 ;
b0 +
b1000 )
0*
b1000 .
b1000 5
b110001 /
b110001 6
b11100111 (
b11100111 4
b1100111 3
10
#1060000
0'
#1065000
0#
b0 "
b0 @
b1000 $
b1000 <
1'
#1066000
1>
b111011110010 =
b110110 ;
b11001010 +
b0 )
1*
b101 .
b101 5
b1010 /
b1010 6
b11001010 (
b11001010 4
b1101000 3
10
#1070000
0'
#1075000
1#
b11001010 "
b11001010 @
b0 $
b0 <
1'
#1076000
0>
b1001 ?
b111111111001 =
b1 ;
b0 +
b1001 )
0*
b111 .
b111 5
b1001000 /
b1001000 6
b11111111 (
b11111111 4
b1101001 3
10
#1080000
0'
#1085000
0#
b0 "
b0 @
b1001 $
b1001 <
1'
#1086000
1>
b111 ?
b1001100000 =
b1001100 ;
b1001100 +
b0 )
1*
b1000 .
b1000 5
b101 /
b101 6
b1001100 (
b1001100 4
b1101010 3
10
#1090000
0'
